Workbook

Sheet Inputs
A1: SyndicUp — Pricing model inputs
A2: Blue cells with yellow fill are inputs — edit them. Everything else recalculates.
A3: FIXED COSTS (MAD / month)
A4: Render (4 × starter, staging + prod) | B4: 280 | C4: ≈ 4 × 7 USD at 10 MAD/USD — render.yaml
A5: Supabase Pro | B5: 250 | C5: 25 USD
A6: Inngest + Upstash + Resend + Sentry + Better Stack | B6: 700 | C6: Estimate at low volume; several have free tiers
A7: Claude subscription | B7: 1000 | C7: Your figure — replace
A8: Apple + Google developer, domains, misc (annualised) | B8: 150 | C8: 99 USD/yr + 25 USD once + domains
A9: Other fixed (accountant, tools) | B9: 600 | C9: Replace with your real number
A10: Total fixed costs | B10: =SUM(B4:B9) -> 2980 | C10: formula
A12: VARIABLE COSTS
A13: SMS cost per message (MAD) | B13: 0.35 | C13: Moroccan aggregator, typical range 0.25–0.50
A14: SMS included per lot per month | B14: 2 | C14: Appel de fonds + one relance
A15: Share of included SMS actually sent | B15: 0.6 | C15: Not every lot gets both messages
A16: Support cost per active residence per month (MAD) | B16: 30 | C16: Your time at ~150 MAD/h, 12 min/residence/month once onboarded
A17: CMI fee on online payments | B17: 0.012 | C17: Your cost; you charge 1.5%
A19: TAX
A20: VAT rate (0 if auto-entrepreneur below threshold) | B20: 0.2 | C20: Prices are TTC; net = TTC / (1+VAT)
A22: PRICE GRID (MAD TTC / lot / month)
A23: Petit — per lot | B23: 6
A24: Petit — monthly floor | B24: 99
A25: Moyen — per lot | B25: 8
A26: Moyen — monthly floor | B26: 390
A27: Grand — per lot | B27: 10
A28: Grand — monthly floor | B28: 990
A29: Cabinet — per lot, < 500 lots | B29: 5
A30: Cabinet — per lot, 500–1 999 lots | B30: 4
A31: Cabinet — per lot, 2 000+ lots | B31: 3
A32: Cabinet — monthly floor | B32: 490
A34: TYPICAL ACCOUNT SIZE (lots)
A35: Petit residence | B35: 14
A36: Moyen residence | B36: 48 | C36: The vitrine example
A37: Grand residence | B37: 110
A38: Cabinet portfolio | B38: 800 | C38: ≈ 20 mandates × 40 lots
A40: TARGETS (MAD / month, net of VAT)
A41: Founder salary target | B41: 15000
A42: Comfortable net target | B42: 50000
A43: Scale net target | B43: 100000
A45: COMPANY — SARL (3 founders)
A46: Accountant / fiduciaire (MAD / month) | B46: 800 | C46: Typical SARL bookkeeping + déclarations TVA/IS
A47: CNSS + AMO employer rate on salaries | B47: 0.2109 | C47: Approx. employer share — confirm with fiduciaire
A48: Corporate tax (IS) rate on profit | B48: 0.2 | C48: 2026 target rate for profit ≤ 100M MAD — confirm; cotisation minimale applies even at a loss
A49: Cotisation minimale (share of turnover, floor 3 000 MAD/yr) | B49: 0.0025 | C49: Confirm current rate with fiduciaire
A51: TEAM & OFFICE TRAJECTORY
A52: Founder salary per founder (MAD gross / month) | B52: 6000 | C52: Recommended: modest first draw, raised as lots grow
A53: Number of founders drawing salary | B53: 3
A54: Month founders start drawing salary | B54: 13 | C54: Recommended trigger: ≥ 4 000 paid lots — see strategy §7b
A55: First hire — onboarding/support (gross / month) | B55: 6000
A56: Month of first hire | B56: 19 | C56: Recommended trigger: ≥ 8 000 lots or > 12 onboardings/month
A57: Second hire — sales / gestionnaire relations (gross / month) | B57: 7000
A58: Month of second hire | B58: 30 | C58: Beyond the 24-month horizon by default
A59: Plateau / office rent + charges (MAD / month) | B59: 5000 | C59: Casablanca plateau ~40–60 m² incl. charges; 0 until the month below
A60: Month office starts | B60: 25 | C60: Recommended: after first hire, not before

Sheet Unit economics
A1: Segment | B1: Lots (typical) | C1: Price / lot TTC | D1: Floor TTC | E1: Monthly bill TTC | F1: Annual bill TTC | G1: Net of VAT / month | H1: SMS cost / month | I1: Support cost / month | J1: Contribution / month | K1: Gross margin % | L1: Net per lot / month
A2: Petit | B2: =Inputs!$B$35 -> 14 | C2: =Inputs!$B$23 -> 6 | D2: =Inputs!$B$24 -> 99 | E2: =MAX(B2*C2,D2) -> 99 | F2: =E2*12 -> 1188 | G2: =E2/(1+Inputs!$B$20) -> 82.5 | H2: =B2*Inputs!$B$14*Inputs!$B$15*Inputs!$B$13 -> 5.88 | I2: =Inputs!$B$16 -> 30 | J2: =G2-H2-I2 -> 46.62 | K2: =IF(G2=0,0,J2/G2) -> 0.56509091 | L2: =IF(B2=0,0,J2/B2) -> 3.33
A3: Moyen | B3: =Inputs!$B$36 -> 48 | C3: =Inputs!$B$25 -> 8 | D3: =Inputs!$B$26 -> 390 | E3: =MAX(B3*C3,D3) -> 390 | F3: =E3*12 -> 4680 | G3: =E3/(1+Inputs!$B$20) -> 325 | H3: =B3*Inputs!$B$14*Inputs!$B$15*Inputs!$B$13 -> 20.16 | I3: =Inputs!$B$16 -> 30 | J3: =G3-H3-I3 -> 274.84 | K3: =IF(G3=0,0,J3/G3) -> 0.84566154 | L3: =IF(B3=0,0,J3/B3) -> 5.7258333
A4: Grand | B4: =Inputs!$B$37 -> 110 | C4: =Inputs!$B$27 -> 10 | D4: =Inputs!$B$28 -> 990 | E4: =MAX(B4*C4,D4) -> 1100 | F4: =E4*12 -> 13200 | G4: =E4/(1+Inputs!$B$20) -> 916.66667 | H4: =B4*Inputs!$B$14*Inputs!$B$15*Inputs!$B$13 -> 46.2 | I4: =Inputs!$B$16 -> 30 | J4: =G4-H4-I4 -> 840.46667 | K4: =IF(G4=0,0,J4/G4) -> 0.91687273 | L4: =IF(B4=0,0,J4/B4) -> 7.6406061
A5: Cabinet | B5: =Inputs!$B$38 -> 800 | C5: =IF(Inputs!$B$38>=2000,Inputs!$B$31,IF(Inputs!$B$38>=500,Inputs!$B$30,Inputs!$B$29)) -> 4 | D5: =Inputs!$B$32 -> 490 | E5: =MAX(B5*C5,D5) -> 3200 | F5: =E5*12 -> 38400 | G5: =E5/(1+Inputs!$B$20) -> 2666.6667 | H5: =B5*Inputs!$B$14*Inputs!$B$15*Inputs!$B$13 -> 336 | I5: =Inputs!$B$16*B5/40*0.5 -> 300 | J5: =G5-H5-I5 -> 2030.6667 | K5: =IF(G5=0,0,J5/G5) -> 0.7615 | L5: =IF(B5=0,0,J5/B5) -> 2.5383333
A7: Notes
A8: Monthly bill = MAX(lots × price, floor). Cabinet support assumed half the per-residence cost (they onboard their own portfolio); portfolio ÷ 40 lots per mandate.
A9: Blended net per lot (weighted by scenario mix) is computed on the Scenarios sheet.

Sheet Break-even
A1: Target (net MAD / month) | B1: Amount | C1: Lots at Moyen net/lot | D1: ≈ Moyen residences | E1: ≈ Cabinets (800 lots)
A2: Cover fixed costs | B2: =Inputs!$B$10 -> 2980 | C2: =B2/'Unit economics'!$L$3 -> 520.44826 | D2: =C2/Inputs!$B$36 -> 10.842672 | E2: =B2/('Unit economics'!$L$5*Inputs!$B$38) -> 1.4674984
A3: Founder salary + fixed | B3: =Inputs!$B$10+Inputs!$B$41 -> 17980 | C3: =B3/'Unit economics'!$L$3 -> 3140.1543 | D3: =C3/Inputs!$B$36 -> 65.419881 | E3: =B3/('Unit economics'!$L$5*Inputs!$B$38) -> 8.8542351
A4: Comfortable net + fixed | B4: =Inputs!$B$10+Inputs!$B$42 -> 52980 | C4: =B4/'Unit economics'!$L$3 -> 9252.8016 | D4: =C4/Inputs!$B$36 -> 192.7667 | E4: =B4/('Unit economics'!$L$5*Inputs!$B$38) -> 26.089954
A5: Scale net + fixed | B5: =Inputs!$B$10+Inputs!$B$43 -> 102980 | C5: =B5/'Unit economics'!$L$3 -> 17985.155 | D5: =C5/Inputs!$B$36 -> 374.69073 | E5: =B5/('Unit economics'!$L$5*Inputs!$B$38) -> 50.71241
A7: Reads: lots needed if every lot were a Moyen residence, or cabinets needed if every lot were cabinet. Reality is a mix — see Scenarios.

Sheet Scenarios
A1: 24-month projection — three adoption scenarios
A2: Inputs: new accounts per month per segment (blue). Churn applied monthly to the active base.
A4: Slow (résistance wins)
A5: New accounts / month — Petit | B5: 1
A6: New accounts / month — Moyen | B6: 1
A7: New accounts / month — Grand | B7: 0.25
A8: New cabinets / month | B8: 0.1
A9: Monthly churn (accounts) | B9: 0.02
A10: Ramp: months 1–3 at 50% of the rate above
A11: Month | B11: 1 | C11: 2 | D11: 3 | E11: 4 | F11: 5 | G11: 6 | H11: 7 | I11: 8 | J11: 9 | K11: 10 | L11: 11 | M11: 12 | N11: 13 | O11: 14 | P11: 15 | Q11: 16 | R11: 17 | S11: 18 | T11: 19 | U11: 20 | V11: 21 | W11: 22 | X11: 23 | Y11: 24
A12: Active Petit accounts | B12: =$B$5*IF(1<=3,0.5,1) -> 0.5 | C12: =B12*(1-$B$9)+$B$5*IF(2<=3,0.5,1) -> 0.99 | D12: =C12*(1-$B$9)+$B$5*IF(3<=3,0.5,1) -> 1.4702 | E12: =D12*(1-$B$9)+$B$5*IF(4<=3,0.5,1) -> 2.440796 | F12: =E12*(1-$B$9)+$B$5*IF(5<=3,0.5,1) -> 3.3919801 | G12: =F12*(1-$B$9)+$B$5*IF(6<=3,0.5,1) -> 4.3241405 | H12: =G12*(1-$B$9)+$B$5*IF(7<=3,0.5,1) -> 5.2376577 | I12: =H12*(1-$B$9)+$B$5*IF(8<=3,0.5,1) -> 6.1329045 | J12: =I12*(1-$B$9)+$B$5*IF(9<=3,0.5,1) -> 7.0102464 | K12: =J12*(1-$B$9)+$B$5*IF(10<=3,0.5,1) -> 7.8700415 | L12: =K12*(1-$B$9)+$B$5*IF(11<=3,0.5,1) -> 8.7126407 | M12: =L12*(1-$B$9)+$B$5*IF(12<=3,0.5,1) -> 9.5383879 | N12: =M12*(1-$B$9)+$B$5*IF(13<=3,0.5,1) -> 10.34762 | O12: =N12*(1-$B$9)+$B$5*IF(14<=3,0.5,1) -> 11.140668 | P12: =O12*(1-$B$9)+$B$5*IF(15<=3,0.5,1) -> 11.917854 | Q12: =P12*(1-$B$9)+$B$5*IF(16<=3,0.5,1) -> 12.679497 | R12: =Q12*(1-$B$9)+$B$5*IF(17<=3,0.5,1) -> 13.425907 | S12: =R12*(1-$B$9)+$B$5*IF(18<=3,0.5,1) -> 14.157389 | T12: =S12*(1-$B$9)+$B$5*IF(19<=3,0.5,1) -> 14.874241 | U12: =T12*(1-$B$9)+$B$5*IF(20<=3,0.5,1) -> 15.576757 | V12: =U12*(1-$B$9)+$B$5*IF(21<=3,0.5,1) -> 16.265221 | W12: =V12*(1-$B$9)+$B$5*IF(22<=3,0.5,1) -> 16.939917 | X12: =W12*(1-$B$9)+$B$5*IF(23<=3,0.5,1) -> 17.601119 | Y12: =X12*(1-$B$9)+$B$5*IF(24<=3,0.5,1) -> 18.249096
A13: Active Moyen accounts | B13: =$B$6*IF(1<=3,0.5,1) -> 0.5 | C13: =B13*(1-$B$9)+$B$6*IF(2<=3,0.5,1) -> 0.99 | D13: =C13*(1-$B$9)+$B$6*IF(3<=3,0.5,1) -> 1.4702 | E13: =D13*(1-$B$9)+$B$6*IF(4<=3,0.5,1) -> 2.440796 | F13: =E13*(1-$B$9)+$B$6*IF(5<=3,0.5,1) -> 3.3919801 | G13: =F13*(1-$B$9)+$B$6*IF(6<=3,0.5,1) -> 4.3241405 | H13: =G13*(1-$B$9)+$B$6*IF(7<=3,0.5,1) -> 5.2376577 | I13: =H13*(1-$B$9)+$B$6*IF(8<=3,0.5,1) -> 6.1329045 | J13: =I13*(1-$B$9)+$B$6*IF(9<=3,0.5,1) -> 7.0102464 | K13: =J13*(1-$B$9)+$B$6*IF(10<=3,0.5,1) -> 7.8700415 | L13: =K13*(1-$B$9)+$B$6*IF(11<=3,0.5,1) -> 8.7126407 | M13: =L13*(1-$B$9)+$B$6*IF(12<=3,0.5,1) -> 9.5383879 | N13: =M13*(1-$B$9)+$B$6*IF(13<=3,0.5,1) -> 10.34762 | O13: =N13*(1-$B$9)+$B$6*IF(14<=3,0.5,1) -> 11.140668 | P13: =O13*(1-$B$9)+$B$6*IF(15<=3,0.5,1) -> 11.917854 | Q13: =P13*(1-$B$9)+$B$6*IF(16<=3,0.5,1) -> 12.679497 | R13: =Q13*(1-$B$9)+$B$6*IF(17<=3,0.5,1) -> 13.425907 | S13: =R13*(1-$B$9)+$B$6*IF(18<=3,0.5,1) -> 14.157389 | T13: =S13*(1-$B$9)+$B$6*IF(19<=3,0.5,1) -> 14.874241 | U13: =T13*(1-$B$9)+$B$6*IF(20<=3,0.5,1) -> 15.576757 | V13: =U13*(1-$B$9)+$B$6*IF(21<=3,0.5,1) -> 16.265221 | W13: =V13*(1-$B$9)+$B$6*IF(22<=3,0.5,1) -> 16.939917 | X13: =W13*(1-$B$9)+$B$6*IF(23<=3,0.5,1) -> 17.601119 | Y13: =X13*(1-$B$9)+$B$6*IF(24<=3,0.5,1) -> 18.249096
A14: Active Grand accounts | B14: =$B$7*IF(1<=3,0.5,1) -> 0.125 | C14: =B14*(1-$B$9)+$B$7*IF(2<=3,0.5,1) -> 0.2475 | D14: =C14*(1-$B$9)+$B$7*IF(3<=3,0.5,1) -> 0.36755 | E14: =D14*(1-$B$9)+$B$7*IF(4<=3,0.5,1) -> 0.610199 | F14: =E14*(1-$B$9)+$B$7*IF(5<=3,0.5,1) -> 0.84799502 | G14: =F14*(1-$B$9)+$B$7*IF(6<=3,0.5,1) -> 1.0810351 | H14: =G14*(1-$B$9)+$B$7*IF(7<=3,0.5,1) -> 1.3094144 | I14: =H14*(1-$B$9)+$B$7*IF(8<=3,0.5,1) -> 1.5332261 | J14: =I14*(1-$B$9)+$B$7*IF(9<=3,0.5,1) -> 1.7525616 | K14: =J14*(1-$B$9)+$B$7*IF(10<=3,0.5,1) -> 1.9675104 | L14: =K14*(1-$B$9)+$B$7*IF(11<=3,0.5,1) -> 2.1781602 | M14: =L14*(1-$B$9)+$B$7*IF(12<=3,0.5,1) -> 2.384597 | N14: =M14*(1-$B$9)+$B$7*IF(13<=3,0.5,1) -> 2.586905 | O14: =N14*(1-$B$9)+$B$7*IF(14<=3,0.5,1) -> 2.7851669 | P14: =O14*(1-$B$9)+$B$7*IF(15<=3,0.5,1) -> 2.9794636 | Q14: =P14*(1-$B$9)+$B$7*IF(16<=3,0.5,1) -> 3.1698743 | R14: =Q14*(1-$B$9)+$B$7*IF(17<=3,0.5,1) -> 3.3564768 | S14: =R14*(1-$B$9)+$B$7*IF(18<=3,0.5,1) -> 3.5393473 | T14: =S14*(1-$B$9)+$B$7*IF(19<=3,0.5,1) -> 3.7185603 | U14: =T14*(1-$B$9)+$B$7*IF(20<=3,0.5,1) -> 3.8941891 | V14: =U14*(1-$B$9)+$B$7*IF(21<=3,0.5,1) -> 4.0663054 | W14: =V14*(1-$B$9)+$B$7*IF(22<=3,0.5,1) -> 4.2349792 | X14: =W14*(1-$B$9)+$B$7*IF(23<=3,0.5,1) -> 4.4002797 | Y14: =X14*(1-$B$9)+$B$7*IF(24<=3,0.5,1) -> 4.5622741
A15: Active cabinets | B15: =$B$8*IF(1<=3,0.5,1) -> 0.05 | C15: =B15*(1-$B$9)+$B$8*IF(2<=3,0.5,1) -> 0.099 | D15: =C15*(1-$B$9)+$B$8*IF(3<=3,0.5,1) -> 0.14702 | E15: =D15*(1-$B$9)+$B$8*IF(4<=3,0.5,1) -> 0.2440796 | F15: =E15*(1-$B$9)+$B$8*IF(5<=3,0.5,1) -> 0.33919801 | G15: =F15*(1-$B$9)+$B$8*IF(6<=3,0.5,1) -> 0.43241405 | H15: =G15*(1-$B$9)+$B$8*IF(7<=3,0.5,1) -> 0.52376577 | I15: =H15*(1-$B$9)+$B$8*IF(8<=3,0.5,1) -> 0.61329045 | J15: =I15*(1-$B$9)+$B$8*IF(9<=3,0.5,1) -> 0.70102464 | K15: =J15*(1-$B$9)+$B$8*IF(10<=3,0.5,1) -> 0.78700415 | L15: =K15*(1-$B$9)+$B$8*IF(11<=3,0.5,1) -> 0.87126407 | M15: =L15*(1-$B$9)+$B$8*IF(12<=3,0.5,1) -> 0.95383879 | N15: =M15*(1-$B$9)+$B$8*IF(13<=3,0.5,1) -> 1.034762 | O15: =N15*(1-$B$9)+$B$8*IF(14<=3,0.5,1) -> 1.1140668 | P15: =O15*(1-$B$9)+$B$8*IF(15<=3,0.5,1) -> 1.1917854 | Q15: =P15*(1-$B$9)+$B$8*IF(16<=3,0.5,1) -> 1.2679497 | R15: =Q15*(1-$B$9)+$B$8*IF(17<=3,0.5,1) -> 1.3425907 | S15: =R15*(1-$B$9)+$B$8*IF(18<=3,0.5,1) -> 1.4157389 | T15: =S15*(1-$B$9)+$B$8*IF(19<=3,0.5,1) -> 1.4874241 | U15: =T15*(1-$B$9)+$B$8*IF(20<=3,0.5,1) -> 1.5576757 | V15: =U15*(1-$B$9)+$B$8*IF(21<=3,0.5,1) -> 1.6265221 | W15: =V15*(1-$B$9)+$B$8*IF(22<=3,0.5,1) -> 1.6939917 | X15: =W15*(1-$B$9)+$B$8*IF(23<=3,0.5,1) -> 1.7601119 | Y15: =X15*(1-$B$9)+$B$8*IF(24<=3,0.5,1) -> 1.8249096
A16: Total paid lots | B16: =B12*Inputs!$B$35+B13*Inputs!$B$36+B14*Inputs!$B$37+B15*Inputs!$B$38 -> 84.75 | C16: =C12*Inputs!$B$35+C13*Inputs!$B$36+C14*Inputs!$B$37+C15*Inputs!$B$38 -> 167.805 | D16: =D12*Inputs!$B$35+D13*Inputs!$B$36+D14*Inputs!$B$37+D15*Inputs!$B$38 -> 249.1989 | E16: =E12*Inputs!$B$35+E13*Inputs!$B$36+E14*Inputs!$B$37+E15*Inputs!$B$38 -> 413.71492 | F16: =F12*Inputs!$B$35+F13*Inputs!$B$36+F14*Inputs!$B$37+F15*Inputs!$B$38 -> 574.94062 | G16: =G12*Inputs!$B$35+G13*Inputs!$B$36+G14*Inputs!$B$37+G15*Inputs!$B$38 -> 732.94181 | H16: =H12*Inputs!$B$35+H13*Inputs!$B$36+H14*Inputs!$B$37+H15*Inputs!$B$38 -> 887.78297 | I16: =I12*Inputs!$B$35+I13*Inputs!$B$36+I14*Inputs!$B$37+I15*Inputs!$B$38 -> 1039.5273 | ... Y16: =Y12*Inputs!$B$35+Y13*Inputs!$B$36+Y14*Inputs!$B$37+Y15*Inputs!$B$38 -> 3093.2218
A17: Revenue TTC (MAD) | B17: =B12*'Unit economics'!$E$2+B13*'Unit economics'!$E$3+B14*'Unit economics'!$E$4+B15*'Unit economics'!$E$5 -> 542 | C17: =C12*'Unit economics'!$E$2+C13*'Unit economics'!$E$3+C14*'Unit economics'!$E$4+C15*'Unit economics'!$E$5 -> 1073.16 | D17: =D12*'Unit economics'!$E$2+D13*'Unit economics'!$E$3+D14*'Unit economics'!$E$4+D15*'Unit economics'!$E$5 -> 1593.6968 | E17: =E12*'Unit economics'!$E$2+E13*'Unit economics'!$E$3+E14*'Unit economics'!$E$4+E15*'Unit economics'!$E$5 -> 2645.8229 | F17: =F12*'Unit economics'!$E$2+F13*'Unit economics'!$E$3+F14*'Unit economics'!$E$4+F15*'Unit economics'!$E$5 -> 3676.9064 | G17: =G12*'Unit economics'!$E$2+G13*'Unit economics'!$E$3+G14*'Unit economics'!$E$4+G15*'Unit economics'!$E$5 -> 4687.3683 | H17: =H12*'Unit economics'!$E$2+H13*'Unit economics'!$E$3+H14*'Unit economics'!$E$4+H15*'Unit economics'!$E$5 -> 5677.6209 | I17: =I12*'Unit economics'!$E$2+I13*'Unit economics'!$E$3+I14*'Unit economics'!$E$4+I15*'Unit economics'!$E$5 -> 6648.0685 | ... Y17: =Y12*'Unit economics'!$E$2+Y13*'Unit economics'!$E$3+Y14*'Unit economics'!$E$4+Y15*'Unit economics'!$E$5 -> 19782.02
A18: Revenue net of VAT | B18: =B17/(1+Inputs!$B$20) -> 451.66667 | C18: =C17/(1+Inputs!$B$20) -> 894.3 | D18: =D17/(1+Inputs!$B$20) -> 1328.0807 | E18: =E17/(1+Inputs!$B$20) -> 2204.8524 | F18: =F17/(1+Inputs!$B$20) -> 3064.0887 | G18: =G17/(1+Inputs!$B$20) -> 3906.1402 | H18: =H17/(1+Inputs!$B$20) -> 4731.3508 | I18: =I17/(1+Inputs!$B$20) -> 5540.0571 | ... Y18: =Y17/(1+Inputs!$B$20) -> 16485.017
A19: Variable costs (SMS + support) | B19: =B12*('Unit economics'!$H$2+'Unit economics'!$I$2)+B13*('Unit economics'!$H$3+'Unit economics'!$I$3)+B14*('Unit economics'!$H$4+'Unit economics'!$I$4)+B15*('Unit economics'!$H$5+'Unit economics'!$I$5) -> 84.345 | C19: =C12*('Unit economics'!$H$2+'Unit economics'!$I$2)+C13*('Unit economics'!$H$3+'Unit economics'!$I$3)+C14*('Unit economics'!$H$4+'Unit economics'!$I$4)+C15*('Unit economics'!$H$5+'Unit economics'!$I$5) -> 167.0031 | D19: =D12*('Unit economics'!$H$2+'Unit economics'!$I$2)+D13*('Unit economics'!$H$3+'Unit economics'!$I$3)+D14*('Unit economics'!$H$4+'Unit economics'!$I$4)+D15*('Unit economics'!$H$5+'Unit economics'!$I$5) -> 248.00804 | E19: =E12*('Unit economics'!$H$2+'Unit economics'!$I$2)+E13*('Unit economics'!$H$3+'Unit economics'!$I$3)+E14*('Unit economics'!$H$4+'Unit economics'!$I$4)+E15*('Unit economics'!$H$5+'Unit economics'!$I$5) -> 411.73788 | F19: =F12*('Unit economics'!$H$2+'Unit economics'!$I$2)+F13*('Unit economics'!$H$3+'Unit economics'!$I$3)+F14*('Unit economics'!$H$4+'Unit economics'!$I$4)+F15*('Unit economics'!$H$5+'Unit economics'!$I$5) -> 572.19312 | G19: =G12*('Unit economics'!$H$2+'Unit economics'!$I$2)+G13*('Unit economics'!$H$3+'Unit economics'!$I$3)+G14*('Unit economics'!$H$4+'Unit economics'!$I$4)+G15*('Unit economics'!$H$5+'Unit economics'!$I$5) -> 729.43926 | H19: =H12*('Unit economics'!$H$2+'Unit economics'!$I$2)+H13*('Unit economics'!$H$3+'Unit economics'!$I$3)+H14*('Unit economics'!$H$4+'Unit economics'!$I$4)+H15*('Unit economics'!$H$5+'Unit economics'!$I$5) -> 883.54047 | I19: =I12*('Unit economics'!$H$2+'Unit economics'!$I$2)+I13*('Unit economics'!$H$3+'Unit economics'!$I$3)+I14*('Unit economics'!$H$4+'Unit economics'!$I$4)+I15*('Unit economics'!$H$5+'Unit economics'!$I$5) -> 1034.5597 | ... Y19: =Y12*('Unit economics'!$H$2+'Unit economics'!$I$2)+Y13*('Unit economics'!$H$3+'Unit economics'!$I$3)+Y14*('Unit economics'!$H$4+'Unit economics'!$I$4)+Y15*('Unit economics'!$H$5+'Unit economics'!$I$5) -> 3078.4401
A20: Infra fixed costs + accountant | B20: =Inputs!$B$10+Inputs!$B$46 -> 3780 | C20: =Inputs!$B$10+Inputs!$B$46 -> 3780 | D20: =Inputs!$B$10+Inputs!$B$46 -> 3780 | E20: =Inputs!$B$10+Inputs!$B$46 -> 3780 | F20: =Inputs!$B$10+Inputs!$B$46 -> 3780 | G20: =Inputs!$B$10+Inputs!$B$46 -> 3780 | H20: =Inputs!$B$10+Inputs!$B$46 -> 3780 | I20: =Inputs!$B$10+Inputs!$B$46 -> 3780 | ... Y20: =Inputs!$B$10+Inputs!$B$46 -> 3780
A21: Founder salaries (incl. CNSS) | B21: =IF(1>=Inputs!$B$54,Inputs!$B$52*Inputs!$B$53*(1+Inputs!$B$47),0) -> 0 | C21: =IF(2>=Inputs!$B$54,Inputs!$B$52*Inputs!$B$53*(1+Inputs!$B$47),0) -> 0 | D21: =IF(3>=Inputs!$B$54,Inputs!$B$52*Inputs!$B$53*(1+Inputs!$B$47),0) -> 0 | E21: =IF(4>=Inputs!$B$54,Inputs!$B$52*Inputs!$B$53*(1+Inputs!$B$47),0) -> 0 | F21: =IF(5>=Inputs!$B$54,Inputs!$B$52*Inputs!$B$53*(1+Inputs!$B$47),0) -> 0 | G21: =IF(6>=Inputs!$B$54,Inputs!$B$52*Inputs!$B$53*(1+Inputs!$B$47),0) -> 0 | H21: =IF(7>=Inputs!$B$54,Inputs!$B$52*Inputs!$B$53*(1+Inputs!$B$47),0) -> 0 | I21: =IF(8>=Inputs!$B$54,Inputs!$B$52*Inputs!$B$53*(1+Inputs!$B$47),0) -> 0 | J21: =IF(9>=Inputs!$B$54,Inputs!$B$52*Inputs!$B$53*(1+Inputs!$B$47),0) -> 0 | K21: =IF(10>=Inputs!$B$54,Inputs!$B$52*Inputs!$B$53*(1+Inputs!$B$47),0) -> 0 | L21: =IF(11>=Inputs!$B$54,Inputs!$B$52*Inputs!$B$53*(1+Inputs!$B$47),0) -> 0 | M21: =IF(12>=Inputs!$B$54,Inputs!$B$52*Inputs!$B$53*(1+Inputs!$B$47),0) -> 0 | N21: =IF(13>=Inputs!$B$54,Inputs!$B$52*Inputs!$B$53*(1+Inputs!$B$47),0) -> 21796.2 | O21: =IF(14>=Inputs!$B$54,Inputs!$B$52*Inputs!$B$53*(1+Inputs!$B$47),0) -> 21796.2 | P21: =IF(15>=Inputs!$B$54,Inputs!$B$52*Inputs!$B$53*(1+Inputs!$B$47),0) -> 21796.2 | Q21: =IF(16>=Inputs!$B$54,Inputs!$B$52*Inputs!$B$53*(1+Inputs!$B$47),0) -> 21796.2 | R21: =IF(17>=Inputs!$B$54,Inputs!$B$52*Inputs!$B$53*(1+Inputs!$B$47),0) -> 21796.2 | S21: =IF(18>=Inputs!$B$54,Inputs!$B$52*Inputs!$B$53*(1+Inputs!$B$47),0) -> 21796.2 | T21: =IF(19>=Inputs!$B$54,Inputs!$B$52*Inputs!$B$53*(1+Inputs!$B$47),0) -> 21796.2 | U21: =IF(20>=Inputs!$B$54,Inputs!$B$52*Inputs!$B$53*(1+Inputs!$B$47),0) -> 21796.2 | V21: =IF(21>=Inputs!$B$54,Inputs!$B$52*Inputs!$B$53*(1+Inputs!$B$47),0) -> 21796.2 | W21: =IF(22>=Inputs!$B$54,Inputs!$B$52*Inputs!$B$53*(1+Inputs!$B$47),0) -> 21796.2 | X21: =IF(23>=Inputs!$B$54,Inputs!$B$52*Inputs!$B$53*(1+Inputs!$B$47),0) -> 21796.2 | Y21: =IF(24>=Inputs!$B$54,Inputs!$B$52*Inputs!$B$53*(1+Inputs!$B$47),0) -> 21796.2
A22: Hires (incl. CNSS) | B22: =IF(1>=Inputs!$B$56,Inputs!$B$55*(1+Inputs!$B$47),0)+IF(1>=Inputs!$B$58,Inputs!$B$57*(1+Inputs!$B$47),0) -> 0 | C22: =IF(2>=Inputs!$B$56,Inputs!$B$55*(1+Inputs!$B$47),0)+IF(2>=Inputs!$B$58,Inputs!$B$57*(1+Inputs!$B$47),0) -> 0 | D22: =IF(3>=Inputs!$B$56,Inputs!$B$55*(1+Inputs!$B$47),0)+IF(3>=Inputs!$B$58,Inputs!$B$57*(1+Inputs!$B$47),0) -> 0 | E22: =IF(4>=Inputs!$B$56,Inputs!$B$55*(1+Inputs!$B$47),0)+IF(4>=Inputs!$B$58,Inputs!$B$57*(1+Inputs!$B$47),0) -> 0 | F22: =IF(5>=Inputs!$B$56,Inputs!$B$55*(1+Inputs!$B$47),0)+IF(5>=Inputs!$B$58,Inputs!$B$57*(1+Inputs!$B$47),0) -> 0 | G22: =IF(6>=Inputs!$B$56,Inputs!$B$55*(1+Inputs!$B$47),0)+IF(6>=Inputs!$B$58,Inputs!$B$57*(1+Inputs!$B$47),0) -> 0 | H22: =IF(7>=Inputs!$B$56,Inputs!$B$55*(1+Inputs!$B$47),0)+IF(7>=Inputs!$B$58,Inputs!$B$57*(1+Inputs!$B$47),0) -> 0 | I22: =IF(8>=Inputs!$B$56,Inputs!$B$55*(1+Inputs!$B$47),0)+IF(8>=Inputs!$B$58,Inputs!$B$57*(1+Inputs!$B$47),0) -> 0 | J22: =IF(9>=Inputs!$B$56,Inputs!$B$55*(1+Inputs!$B$47),0)+IF(9>=Inputs!$B$58,Inputs!$B$57*(1+Inputs!$B$47),0) -> 0 | K22: =IF(10>=Inputs!$B$56,Inputs!$B$55*(1+Inputs!$B$47),0)+IF(10>=Inputs!$B$58,Inputs!$B$57*(1+Inputs!$B$47),0) -> 0 | L22: =IF(11>=Inputs!$B$56,Inputs!$B$55*(1+Inputs!$B$47),0)+IF(11>=Inputs!$B$58,Inputs!$B$57*(1+Inputs!$B$47),0) -> 0 | M22: =IF(12>=Inputs!$B$56,Inputs!$B$55*(1+Inputs!$B$47),0)+IF(12>=Inputs!$B$58,Inputs!$B$57*(1+Inputs!$B$47),0) -> 0 | N22: =IF(13>=Inputs!$B$56,Inputs!$B$55*(1+Inputs!$B$47),0)+IF(13>=Inputs!$B$58,Inputs!$B$57*(1+Inputs!$B$47),0) -> 0 | O22: =IF(14>=Inputs!$B$56,Inputs!$B$55*(1+Inputs!$B$47),0)+IF(14>=Inputs!$B$58,Inputs!$B$57*(1+Inputs!$B$47),0) -> 0 | P22: =IF(15>=Inputs!$B$56,Inputs!$B$55*(1+Inputs!$B$47),0)+IF(15>=Inputs!$B$58,Inputs!$B$57*(1+Inputs!$B$47),0) -> 0 | Q22: =IF(16>=Inputs!$B$56,Inputs!$B$55*(1+Inputs!$B$47),0)+IF(16>=Inputs!$B$58,Inputs!$B$57*(1+Inputs!$B$47),0) -> 0 | R22: =IF(17>=Inputs!$B$56,Inputs!$B$55*(1+Inputs!$B$47),0)+IF(17>=Inputs!$B$58,Inputs!$B$57*(1+Inputs!$B$47),0) -> 0 | S22: =IF(18>=Inputs!$B$56,Inputs!$B$55*(1+Inputs!$B$47),0)+IF(18>=Inputs!$B$58,Inputs!$B$57*(1+Inputs!$B$47),0) -> 0 | T22: =IF(19>=Inputs!$B$56,Inputs!$B$55*(1+Inputs!$B$47),0)+IF(19>=Inputs!$B$58,Inputs!$B$57*(1+Inputs!$B$47),0) -> 7265.4 | U22: =IF(20>=Inputs!$B$56,Inputs!$B$55*(1+Inputs!$B$47),0)+IF(20>=Inputs!$B$58,Inputs!$B$57*(1+Inputs!$B$47),0) -> 7265.4 | V22: =IF(21>=Inputs!$B$56,Inputs!$B$55*(1+Inputs!$B$47),0)+IF(21>=Inputs!$B$58,Inputs!$B$57*(1+Inputs!$B$47),0) -> 7265.4 | W22: =IF(22>=Inputs!$B$56,Inputs!$B$55*(1+Inputs!$B$47),0)+IF(22>=Inputs!$B$58,Inputs!$B$57*(1+Inputs!$B$47),0) -> 7265.4 | X22: =IF(23>=Inputs!$B$56,Inputs!$B$55*(1+Inputs!$B$47),0)+IF(23>=Inputs!$B$58,Inputs!$B$57*(1+Inputs!$B$47),0) -> 7265.4 | Y22: =IF(24>=Inputs!$B$56,Inputs!$B$55*(1+Inputs!$B$47),0)+IF(24>=Inputs!$B$58,Inputs!$B$57*(1+Inputs!$B$47),0) -> 7265.4
A23: Office | B23: =IF(1>=Inputs!$B$60,Inputs!$B$59,0) -> 0 | C23: =IF(2>=Inputs!$B$60,Inputs!$B$59,0) -> 0 | D23: =IF(3>=Inputs!$B$60,Inputs!$B$59,0) -> 0 | E23: =IF(4>=Inputs!$B$60,Inputs!$B$59,0) -> 0 | F23: =IF(5>=Inputs!$B$60,Inputs!$B$59,0) -> 0 | G23: =IF(6>=Inputs!$B$60,Inputs!$B$59,0) -> 0 | H23: =IF(7>=Inputs!$B$60,Inputs!$B$59,0) -> 0 | I23: =IF(8>=Inputs!$B$60,Inputs!$B$59,0) -> 0 | J23: =IF(9>=Inputs!$B$60,Inputs!$B$59,0) -> 0 | K23: =IF(10>=Inputs!$B$60,Inputs!$B$59,0) -> 0 | L23: =IF(11>=Inputs!$B$60,Inputs!$B$59,0) -> 0 | M23: =IF(12>=Inputs!$B$60,Inputs!$B$59,0) -> 0 | N23: =IF(13>=Inputs!$B$60,Inputs!$B$59,0) -> 0 | O23: =IF(14>=Inputs!$B$60,Inputs!$B$59,0) -> 0 | P23: =IF(15>=Inputs!$B$60,Inputs!$B$59,0) -> 0 | Q23: =IF(16>=Inputs!$B$60,Inputs!$B$59,0) -> 0 | R23: =IF(17>=Inputs!$B$60,Inputs!$B$59,0) -> 0 | S23: =IF(18>=Inputs!$B$60,Inputs!$B$59,0) -> 0 | T23: =IF(19>=Inputs!$B$60,Inputs!$B$59,0) -> 0 | U23: =IF(20>=Inputs!$B$60,Inputs!$B$59,0) -> 0 | V23: =IF(21>=Inputs!$B$60,Inputs!$B$59,0) -> 0 | W23: =IF(22>=Inputs!$B$60,Inputs!$B$59,0) -> 0 | X23: =IF(23>=Inputs!$B$60,Inputs!$B$59,0) -> 0 | Y23: =IF(24>=Inputs!$B$60,Inputs!$B$59,0) -> 0
A24: Result before tax (MAD) | B24: =B18-B19-B20-B21-B22-B23 -> -3412.6783 | C24: =C18-C19-C20-C21-C22-C23 -> -3052.7031 | D24: =D18-D19-D20-D21-D22-D23 -> -2699.9274 | E24: =E18-E19-E20-E21-E22-E23 -> -1986.8855 | F24: =F18-F19-F20-F21-F22-F23 -> -1288.1044 | G24: =G18-G19-G20-G21-G22-G23 -> -603.29903 | H24: =H18-H19-H20-H21-H22-H23 -> 67.810289 | I24: =I18-I19-I20-I21-I22-I23 -> 725.49742 | ... Y24: =Y18-Y19-Y20-Y21-Y22-Y23 -> -19435.023
A25: IS + cotisation minimale | B25: =MAX(B24*Inputs!$B$48,MAX(B18*Inputs!$B$49,250)) -> 250 | C25: =MAX(C24*Inputs!$B$48,MAX(C18*Inputs!$B$49,250)) -> 250 | D25: =MAX(D24*Inputs!$B$48,MAX(D18*Inputs!$B$49,250)) -> 250 | E25: =MAX(E24*Inputs!$B$48,MAX(E18*Inputs!$B$49,250)) -> 250 | F25: =MAX(F24*Inputs!$B$48,MAX(F18*Inputs!$B$49,250)) -> 250 | G25: =MAX(G24*Inputs!$B$48,MAX(G18*Inputs!$B$49,250)) -> 250 | H25: =MAX(H24*Inputs!$B$48,MAX(H18*Inputs!$B$49,250)) -> 250 | I25: =MAX(I24*Inputs!$B$48,MAX(I18*Inputs!$B$49,250)) -> 250 | ... Y25: =MAX(Y24*Inputs!$B$48,MAX(Y18*Inputs!$B$49,250)) -> 250
A26: Net result after tax | B26: =B24-B25 -> -3662.6783 | C26: =C24-C25 -> -3302.7031 | D26: =D24-D25 -> -2949.9274 | E26: =E24-E25 -> -2236.8855 | F26: =F24-F25 -> -1538.1044 | G26: =G24-G25 -> -853.29903 | H26: =H24-H25 -> -182.18971 | I26: =I24-I25 -> 475.49742 | ... Y26: =Y24-Y25 -> -19685.023
A27: Cumulative net after tax | B27: =B26 -> -3662.6783 | C27: =B27+C26 -> -6965.3814 | D27: =C27+D26 -> -9915.3088 | E27: =D27+E26 -> -12152.194 | F27: =E27+F26 -> -13690.299 | G27: =F27+G26 -> -14543.598 | H27: =G27+H26 -> -14725.787 | I27: =H27+I26 -> -14250.29 | J27: =I27+J26 -> -13154.265 | ... Y27: =X27+Y26 -> -233159.26
A30: Base (plan works)
A31: New accounts / month — Petit | B31: 2
A32: New accounts / month — Moyen | B32: 3
A33: New accounts / month — Grand | B33: 0.5
A34: New cabinets / month | B34: 0.3
A35: Monthly churn (accounts) | B35: 0.015
A36: Ramp: months 1–3 at 50% of the rate above
A37: Month | B37: 1 | C37: 2 | D37: 3 | E37: 4 | F37: 5 | G37: 6 | H37: 7 | I37: 8 | J37: 9 | K37: 10 | L37: 11 | M37: 12 | N37: 13 | O37: 14 | P37: 15 | Q37: 16 | R37: 17 | S37: 18 | T37: 19 | U37: 20 | V37: 21 | W37: 22 | X37: 23 | Y37: 24
A38: Active Petit accounts | B38: =$B$31*IF(1<=3,0.5,1) -> 1 | C38: =B38*(1-$B$35)+$B$31*IF(2<=3,0.5,1) -> 1.985 | D38: =C38*(1-$B$35)+$B$31*IF(3<=3,0.5,1) -> 2.955225 | E38: =D38*(1-$B$35)+$B$31*IF(4<=3,0.5,1) -> 4.9108966 | F38: =E38*(1-$B$35)+$B$31*IF(5<=3,0.5,1) -> 6.8372332 | G38: =F38*(1-$B$35)+$B$31*IF(6<=3,0.5,1) -> 8.7346747 | H38: =G38*(1-$B$35)+$B$31*IF(7<=3,0.5,1) -> 10.603655 | I38: =H38*(1-$B$35)+$B$31*IF(8<=3,0.5,1) -> 12.4446 | J38: =I38*(1-$B$35)+$B$31*IF(9<=3,0.5,1) -> 14.257931 | K38: =J38*(1-$B$35)+$B$31*IF(10<=3,0.5,1) -> 16.044062 | L38: =K38*(1-$B$35)+$B$31*IF(11<=3,0.5,1) -> 17.803401 | M38: =L38*(1-$B$35)+$B$31*IF(12<=3,0.5,1) -> 19.53635 | N38: =M38*(1-$B$35)+$B$31*IF(13<=3,0.5,1) -> 21.243305 | O38: =N38*(1-$B$35)+$B$31*IF(14<=3,0.5,1) -> 22.924655 | P38: =O38*(1-$B$35)+$B$31*IF(15<=3,0.5,1) -> 24.580785 | Q38: =P38*(1-$B$35)+$B$31*IF(16<=3,0.5,1) -> 26.212073 | R38: =Q38*(1-$B$35)+$B$31*IF(17<=3,0.5,1) -> 27.818892 | S38: =R38*(1-$B$35)+$B$31*IF(18<=3,0.5,1) -> 29.401609 | T38: =S38*(1-$B$35)+$B$31*IF(19<=3,0.5,1) -> 30.960585 | U38: =T38*(1-$B$35)+$B$31*IF(20<=3,0.5,1) -> 32.496176 | V38: =U38*(1-$B$35)+$B$31*IF(21<=3,0.5,1) -> 34.008733 | W38: =V38*(1-$B$35)+$B$31*IF(22<=3,0.5,1) -> 35.498602 | X38: =W38*(1-$B$35)+$B$31*IF(23<=3,0.5,1) -> 36.966123 | Y38: =X38*(1-$B$35)+$B$31*IF(24<=3,0.5,1) -> 38.411632
A39: Active Moyen accounts | B39: =$B$32*IF(1<=3,0.5,1) -> 1.5 | C39: =B39*(1-$B$35)+$B$32*IF(2<=3,0.5,1) -> 2.9775 | D39: =C39*(1-$B$35)+$B$32*IF(3<=3,0.5,1) -> 4.4328375 | E39: =D39*(1-$B$35)+$B$32*IF(4<=3,0.5,1) -> 7.3663449 | F39: =E39*(1-$B$35)+$B$32*IF(5<=3,0.5,1) -> 10.25585 | G39: =F39*(1-$B$35)+$B$32*IF(6<=3,0.5,1) -> 13.102012 | H39: =G39*(1-$B$35)+$B$32*IF(7<=3,0.5,1) -> 15.905482 | I39: =H39*(1-$B$35)+$B$32*IF(8<=3,0.5,1) -> 18.6669 | J39: =I39*(1-$B$35)+$B$32*IF(9<=3,0.5,1) -> 21.386896 | K39: =J39*(1-$B$35)+$B$32*IF(10<=3,0.5,1) -> 24.066093 | L39: =K39*(1-$B$35)+$B$32*IF(11<=3,0.5,1) -> 26.705101 | M39: =L39*(1-$B$35)+$B$32*IF(12<=3,0.5,1) -> 29.304525 | N39: =M39*(1-$B$35)+$B$32*IF(13<=3,0.5,1) -> 31.864957 | O39: =N39*(1-$B$35)+$B$32*IF(14<=3,0.5,1) -> 34.386983 | P39: =O39*(1-$B$35)+$B$32*IF(15<=3,0.5,1) -> 36.871178 | Q39: =P39*(1-$B$35)+$B$32*IF(16<=3,0.5,1) -> 39.31811 | R39: =Q39*(1-$B$35)+$B$32*IF(17<=3,0.5,1) -> 41.728338 | S39: =R39*(1-$B$35)+$B$32*IF(18<=3,0.5,1) -> 44.102413 | T39: =S39*(1-$B$35)+$B$32*IF(19<=3,0.5,1) -> 46.440877 | U39: =T39*(1-$B$35)+$B$32*IF(20<=3,0.5,1) -> 48.744264 | V39: =U39*(1-$B$35)+$B$32*IF(21<=3,0.5,1) -> 51.0131 | W39: =V39*(1-$B$35)+$B$32*IF(22<=3,0.5,1) -> 53.247904 | X39: =W39*(1-$B$35)+$B$32*IF(23<=3,0.5,1) -> 55.449185 | Y39: =X39*(1-$B$35)+$B$32*IF(24<=3,0.5,1) -> 57.617447
A40: Active Grand accounts | B40: =$B$33*IF(1<=3,0.5,1) -> 0.25 | C40: =B40*(1-$B$35)+$B$33*IF(2<=3,0.5,1) -> 0.49625 | D40: =C40*(1-$B$35)+$B$33*IF(3<=3,0.5,1) -> 0.73880625 | E40: =D40*(1-$B$35)+$B$33*IF(4<=3,0.5,1) -> 1.2277242 | F40: =E40*(1-$B$35)+$B$33*IF(5<=3,0.5,1) -> 1.7093083 | G40: =F40*(1-$B$35)+$B$33*IF(6<=3,0.5,1) -> 2.1836687 | H40: =G40*(1-$B$35)+$B$33*IF(7<=3,0.5,1) -> 2.6509136 | I40: =H40*(1-$B$35)+$B$33*IF(8<=3,0.5,1) -> 3.1111499 | J40: =I40*(1-$B$35)+$B$33*IF(9<=3,0.5,1) -> 3.5644827 | K40: =J40*(1-$B$35)+$B$33*IF(10<=3,0.5,1) -> 4.0110154 | L40: =K40*(1-$B$35)+$B$33*IF(11<=3,0.5,1) -> 4.4508502 | M40: =L40*(1-$B$35)+$B$33*IF(12<=3,0.5,1) -> 4.8840875 | N40: =M40*(1-$B$35)+$B$33*IF(13<=3,0.5,1) -> 5.3108261 | O40: =N40*(1-$B$35)+$B$33*IF(14<=3,0.5,1) -> 5.7311638 | P40: =O40*(1-$B$35)+$B$33*IF(15<=3,0.5,1) -> 6.1451963 | Q40: =P40*(1-$B$35)+$B$33*IF(16<=3,0.5,1) -> 6.5530184 | R40: =Q40*(1-$B$35)+$B$33*IF(17<=3,0.5,1) -> 6.9547231 | S40: =R40*(1-$B$35)+$B$33*IF(18<=3,0.5,1) -> 7.3504022 | T40: =S40*(1-$B$35)+$B$33*IF(19<=3,0.5,1) -> 7.7401462 | U40: =T40*(1-$B$35)+$B$33*IF(20<=3,0.5,1) -> 8.124044 | V40: =U40*(1-$B$35)+$B$33*IF(21<=3,0.5,1) -> 8.5021833 | W40: =V40*(1-$B$35)+$B$33*IF(22<=3,0.5,1) -> 8.8746506 | X40: =W40*(1-$B$35)+$B$33*IF(23<=3,0.5,1) -> 9.2415308 | Y40: =X40*(1-$B$35)+$B$33*IF(24<=3,0.5,1) -> 9.6029079
A41: Active cabinets | B41: =$B$34*IF(1<=3,0.5,1) -> 0.15 | C41: =B41*(1-$B$35)+$B$34*IF(2<=3,0.5,1) -> 0.29775 | D41: =C41*(1-$B$35)+$B$34*IF(3<=3,0.5,1) -> 0.44328375 | E41: =D41*(1-$B$35)+$B$34*IF(4<=3,0.5,1) -> 0.73663449 | F41: =E41*(1-$B$35)+$B$34*IF(5<=3,0.5,1) -> 1.025585 | G41: =F41*(1-$B$35)+$B$34*IF(6<=3,0.5,1) -> 1.3102012 | H41: =G41*(1-$B$35)+$B$34*IF(7<=3,0.5,1) -> 1.5905482 | I41: =H41*(1-$B$35)+$B$34*IF(8<=3,0.5,1) -> 1.86669 | J41: =I41*(1-$B$35)+$B$34*IF(9<=3,0.5,1) -> 2.1386896 | K41: =J41*(1-$B$35)+$B$34*IF(10<=3,0.5,1) -> 2.4066093 | L41: =K41*(1-$B$35)+$B$34*IF(11<=3,0.5,1) -> 2.6705101 | M41: =L41*(1-$B$35)+$B$34*IF(12<=3,0.5,1) -> 2.9304525 | N41: =M41*(1-$B$35)+$B$34*IF(13<=3,0.5,1) -> 3.1864957 | O41: =N41*(1-$B$35)+$B$34*IF(14<=3,0.5,1) -> 3.4386983 | P41: =O41*(1-$B$35)+$B$34*IF(15<=3,0.5,1) -> 3.6871178 | Q41: =P41*(1-$B$35)+$B$34*IF(16<=3,0.5,1) -> 3.931811 | R41: =Q41*(1-$B$35)+$B$34*IF(17<=3,0.5,1) -> 4.1728338 | S41: =R41*(1-$B$35)+$B$34*IF(18<=3,0.5,1) -> 4.4102413 | T41: =S41*(1-$B$35)+$B$34*IF(19<=3,0.5,1) -> 4.6440877 | U41: =T41*(1-$B$35)+$B$34*IF(20<=3,0.5,1) -> 4.8744264 | V41: =U41*(1-$B$35)+$B$34*IF(21<=3,0.5,1) -> 5.10131 | W41: =V41*(1-$B$35)+$B$34*IF(22<=3,0.5,1) -> 5.3247904 | X41: =W41*(1-$B$35)+$B$34*IF(23<=3,0.5,1) -> 5.5449185 | Y41: =X41*(1-$B$35)+$B$34*IF(24<=3,0.5,1) -> 5.7617447
A42: Total paid lots | B42: =B38*Inputs!$B$35+B39*Inputs!$B$36+B40*Inputs!$B$37+B41*Inputs!$B$38 -> 233.5 | C42: =C38*Inputs!$B$35+C39*Inputs!$B$36+C40*Inputs!$B$37+C41*Inputs!$B$38 -> 463.4975 | D42: =D38*Inputs!$B$35+D39*Inputs!$B$36+D40*Inputs!$B$37+D41*Inputs!$B$38 -> 690.04504 | E42: =E38*Inputs!$B$35+E39*Inputs!$B$36+E40*Inputs!$B$37+E41*Inputs!$B$38 -> 1146.6944 | F42: =F38*Inputs!$B$35+F39*Inputs!$B$36+F40*Inputs!$B$37+F41*Inputs!$B$38 -> 1596.4939 | G42: =G38*Inputs!$B$35+G39*Inputs!$B$36+G40*Inputs!$B$37+G41*Inputs!$B$38 -> 2039.5465 | H42: =H38*Inputs!$B$35+H39*Inputs!$B$36+H40*Inputs!$B$37+H41*Inputs!$B$38 -> 2475.9533 | I42: =I38*Inputs!$B$35+I39*Inputs!$B$36+I40*Inputs!$B$37+I41*Inputs!$B$38 -> 2905.814 | ... Y42: =Y38*Inputs!$B$35+Y39*Inputs!$B$36+Y40*Inputs!$B$37+Y41*Inputs!$B$38 -> 8969.116
A43: Revenue TTC (MAD) | B43: =B38*'Unit economics'!$E$2+B39*'Unit economics'!$E$3+B40*'Unit economics'!$E$4+B41*'Unit economics'!$E$5 -> 1439 | C43: =C38*'Unit economics'!$E$2+C39*'Unit economics'!$E$3+C40*'Unit economics'!$E$4+C41*'Unit economics'!$E$5 -> 2856.415 | D43: =D38*'Unit economics'!$E$2+D39*'Unit economics'!$E$3+D40*'Unit economics'!$E$4+D41*'Unit economics'!$E$5 -> 4252.5688 | E43: =E38*'Unit economics'!$E$2+E39*'Unit economics'!$E$3+E40*'Unit economics'!$E$4+E41*'Unit economics'!$E$5 -> 7066.7802 | F43: =F38*'Unit economics'!$E$2+F39*'Unit economics'!$E$3+F40*'Unit economics'!$E$4+F41*'Unit economics'!$E$5 -> 9838.7785 | G43: =G38*'Unit economics'!$E$2+G39*'Unit economics'!$E$3+G40*'Unit economics'!$E$4+G41*'Unit economics'!$E$5 -> 12569.197 | H43: =H38*'Unit economics'!$E$2+H39*'Unit economics'!$E$3+H40*'Unit economics'!$E$4+H41*'Unit economics'!$E$5 -> 15258.659 | I43: =I38*'Unit economics'!$E$2+I39*'Unit economics'!$E$3+I40*'Unit economics'!$E$4+I41*'Unit economics'!$E$5 -> 17907.779 | ... Y43: =Y38*'Unit economics'!$E$2+Y39*'Unit economics'!$E$3+Y40*'Unit economics'!$E$4+Y41*'Unit economics'!$E$5 -> 55274.338
A44: Revenue net of VAT | B44: =B43/(1+Inputs!$B$20) -> 1199.1667 | C44: =C43/(1+Inputs!$B$20) -> 2380.3458 | D44: =D43/(1+Inputs!$B$20) -> 3543.8073 | E44: =E43/(1+Inputs!$B$20) -> 5888.9835 | F44: =F43/(1+Inputs!$B$20) -> 8198.9821 | G44: =G43/(1+Inputs!$B$20) -> 10474.331 | H44: =H43/(1+Inputs!$B$20) -> 12715.549 | I44: =I43/(1+Inputs!$B$20) -> 14923.149 | ... Y44: =Y43/(1+Inputs!$B$20) -> 46061.948
A45: Variable costs (SMS + support) | B45: =B38*('Unit economics'!$H$2+'Unit economics'!$I$2)+B39*('Unit economics'!$H$3+'Unit economics'!$I$3)+B40*('Unit economics'!$H$4+'Unit economics'!$I$4)+B41*('Unit economics'!$H$5+'Unit economics'!$I$5) -> 225.57 | C45: =C38*('Unit economics'!$H$2+'Unit economics'!$I$2)+C39*('Unit economics'!$H$3+'Unit economics'!$I$3)+C40*('Unit economics'!$H$4+'Unit economics'!$I$4)+C41*('Unit economics'!$H$5+'Unit economics'!$I$5) -> 447.75645 | D45: =D38*('Unit economics'!$H$2+'Unit economics'!$I$2)+D39*('Unit economics'!$H$3+'Unit economics'!$I$3)+D40*('Unit economics'!$H$4+'Unit economics'!$I$4)+D41*('Unit economics'!$H$5+'Unit economics'!$I$5) -> 666.6101 | E45: =E38*('Unit economics'!$H$2+'Unit economics'!$I$2)+E39*('Unit economics'!$H$3+'Unit economics'!$I$3)+E40*('Unit economics'!$H$4+'Unit economics'!$I$4)+E41*('Unit economics'!$H$5+'Unit economics'!$I$5) -> 1107.751 | F45: =F38*('Unit economics'!$H$2+'Unit economics'!$I$2)+F39*('Unit economics'!$H$3+'Unit economics'!$I$3)+F40*('Unit economics'!$H$4+'Unit economics'!$I$4)+F41*('Unit economics'!$H$5+'Unit economics'!$I$5) -> 1542.2747 | G45: =G38*('Unit economics'!$H$2+'Unit economics'!$I$2)+G39*('Unit economics'!$H$3+'Unit economics'!$I$3)+G40*('Unit economics'!$H$4+'Unit economics'!$I$4)+G41*('Unit economics'!$H$5+'Unit economics'!$I$5) -> 1970.2806 | H45: =H38*('Unit economics'!$H$2+'Unit economics'!$I$2)+H39*('Unit economics'!$H$3+'Unit economics'!$I$3)+H40*('Unit economics'!$H$4+'Unit economics'!$I$4)+H41*('Unit economics'!$H$5+'Unit economics'!$I$5) -> 2391.8664 | I45: =I38*('Unit economics'!$H$2+'Unit economics'!$I$2)+I39*('Unit economics'!$H$3+'Unit economics'!$I$3)+I40*('Unit economics'!$H$4+'Unit economics'!$I$4)+I41*('Unit economics'!$H$5+'Unit economics'!$I$5) -> 2807.1284 | ... Y45: =Y38*('Unit economics'!$H$2+'Unit economics'!$I$2)+Y39*('Unit economics'!$H$3+'Unit economics'!$I$3)+Y40*('Unit economics'!$H$4+'Unit economics'!$I$4)+Y41*('Unit economics'!$H$5+'Unit economics'!$I$5) -> 8664.5117
A46: Infra fixed costs + accountant | B46: =Inputs!$B$10+Inputs!$B$46 -> 3780 | C46: =Inputs!$B$10+Inputs!$B$46 -> 3780 | D46: =Inputs!$B$10+Inputs!$B$46 -> 3780 | E46: =Inputs!$B$10+Inputs!$B$46 -> 3780 | F46: =Inputs!$B$10+Inputs!$B$46 -> 3780 | G46: =Inputs!$B$10+Inputs!$B$46 -> 3780 | H46: =Inputs!$B$10+Inputs!$B$46 -> 3780 | I46: =Inputs!$B$10+Inputs!$B$46 -> 3780 | ... Y46: =Inputs!$B$10+Inputs!$B$46 -> 3780
A47: Founder salaries (incl. CNSS) | B47: =IF(1>=Inputs!$B$54,Inputs!$B$52*Inputs!$B$53*(1+Inputs!$B$47),0) -> 0 | C47: =IF(2>=Inputs!$B$54,Inputs!$B$52*Inputs!$B$53*(1+Inputs!$B$47),0) -> 0 | D47: =IF(3>=Inputs!$B$54,Inputs!$B$52*Inputs!$B$53*(1+Inputs!$B$47),0) -> 0 | E47: =IF(4>=Inputs!$B$54,Inputs!$B$52*Inputs!$B$53*(1+Inputs!$B$47),0) -> 0 | F47: =IF(5>=Inputs!$B$54,Inputs!$B$52*Inputs!$B$53*(1+Inputs!$B$47),0) -> 0 | G47: =IF(6>=Inputs!$B$54,Inputs!$B$52*Inputs!$B$53*(1+Inputs!$B$47),0) -> 0 | H47: =IF(7>=Inputs!$B$54,Inputs!$B$52*Inputs!$B$53*(1+Inputs!$B$47),0) -> 0 | I47: =IF(8>=Inputs!$B$54,Inputs!$B$52*Inputs!$B$53*(1+Inputs!$B$47),0) -> 0 | J47: =IF(9>=Inputs!$B$54,Inputs!$B$52*Inputs!$B$53*(1+Inputs!$B$47),0) -> 0 | K47: =IF(10>=Inputs!$B$54,Inputs!$B$52*Inputs!$B$53*(1+Inputs!$B$47),0) -> 0 | L47: =IF(11>=Inputs!$B$54,Inputs!$B$52*Inputs!$B$53*(1+Inputs!$B$47),0) -> 0 | M47: =IF(12>=Inputs!$B$54,Inputs!$B$52*Inputs!$B$53*(1+Inputs!$B$47),0) -> 0 | N47: =IF(13>=Inputs!$B$54,Inputs!$B$52*Inputs!$B$53*(1+Inputs!$B$47),0) -> 21796.2 | O47: =IF(14>=Inputs!$B$54,Inputs!$B$52*Inputs!$B$53*(1+Inputs!$B$47),0) -> 21796.2 | P47: =IF(15>=Inputs!$B$54,Inputs!$B$52*Inputs!$B$53*(1+Inputs!$B$47),0) -> 21796.2 | Q47: =IF(16>=Inputs!$B$54,Inputs!$B$52*Inputs!$B$53*(1+Inputs!$B$47),0) -> 21796.2 | R47: =IF(17>=Inputs!$B$54,Inputs!$B$52*Inputs!$B$53*(1+Inputs!$B$47),0) -> 21796.2 | S47: =IF(18>=Inputs!$B$54,Inputs!$B$52*Inputs!$B$53*(1+Inputs!$B$47),0) -> 21796.2 | T47: =IF(19>=Inputs!$B$54,Inputs!$B$52*Inputs!$B$53*(1+Inputs!$B$47),0) -> 21796.2 | U47: =IF(20>=Inputs!$B$54,Inputs!$B$52*Inputs!$B$53*(1+Inputs!$B$47),0) -> 21796.2 | V47: =IF(21>=Inputs!$B$54,Inputs!$B$52*Inputs!$B$53*(1+Inputs!$B$47),0) -> 21796.2 | W47: =IF(22>=Inputs!$B$54,Inputs!$B$52*Inputs!$B$53*(1+Inputs!$B$47),0) -> 21796.2 | X47: =IF(23>=Inputs!$B$54,Inputs!$B$52*Inputs!$B$53*(1+Inputs!$B$47),0) -> 21796.2 | Y47: =IF(24>=Inputs!$B$54,Inputs!$B$52*Inputs!$B$53*(1+Inputs!$B$47),0) -> 21796.2
A48: Hires (incl. CNSS) | B48: =IF(1>=Inputs!$B$56,Inputs!$B$55*(1+Inputs!$B$47),0)+IF(1>=Inputs!$B$58,Inputs!$B$57*(1+Inputs!$B$47),0) -> 0 | C48: =IF(2>=Inputs!$B$56,Inputs!$B$55*(1+Inputs!$B$47),0)+IF(2>=Inputs!$B$58,Inputs!$B$57*(1+Inputs!$B$47),0) -> 0 | D48: =IF(3>=Inputs!$B$56,Inputs!$B$55*(1+Inputs!$B$47),0)+IF(3>=Inputs!$B$58,Inputs!$B$57*(1+Inputs!$B$47),0) -> 0 | E48: =IF(4>=Inputs!$B$56,Inputs!$B$55*(1+Inputs!$B$47),0)+IF(4>=Inputs!$B$58,Inputs!$B$57*(1+Inputs!$B$47),0) -> 0 | F48: =IF(5>=Inputs!$B$56,Inputs!$B$55*(1+Inputs!$B$47),0)+IF(5>=Inputs!$B$58,Inputs!$B$57*(1+Inputs!$B$47),0) -> 0 | G48: =IF(6>=Inputs!$B$56,Inputs!$B$55*(1+Inputs!$B$47),0)+IF(6>=Inputs!$B$58,Inputs!$B$57*(1+Inputs!$B$47),0) -> 0 | H48: =IF(7>=Inputs!$B$56,Inputs!$B$55*(1+Inputs!$B$47),0)+IF(7>=Inputs!$B$58,Inputs!$B$57*(1+Inputs!$B$47),0) -> 0 | I48: =IF(8>=Inputs!$B$56,Inputs!$B$55*(1+Inputs!$B$47),0)+IF(8>=Inputs!$B$58,Inputs!$B$57*(1+Inputs!$B$47),0) -> 0 | J48: =IF(9>=Inputs!$B$56,Inputs!$B$55*(1+Inputs!$B$47),0)+IF(9>=Inputs!$B$58,Inputs!$B$57*(1+Inputs!$B$47),0) -> 0 | K48: =IF(10>=Inputs!$B$56,Inputs!$B$55*(1+Inputs!$B$47),0)+IF(10>=Inputs!$B$58,Inputs!$B$57*(1+Inputs!$B$47),0) -> 0 | L48: =IF(11>=Inputs!$B$56,Inputs!$B$55*(1+Inputs!$B$47),0)+IF(11>=Inputs!$B$58,Inputs!$B$57*(1+Inputs!$B$47),0) -> 0 | M48: =IF(12>=Inputs!$B$56,Inputs!$B$55*(1+Inputs!$B$47),0)+IF(12>=Inputs!$B$58,Inputs!$B$57*(1+Inputs!$B$47),0) -> 0 | N48: =IF(13>=Inputs!$B$56,Inputs!$B$55*(1+Inputs!$B$47),0)+IF(13>=Inputs!$B$58,Inputs!$B$57*(1+Inputs!$B$47),0) -> 0 | O48: =IF(14>=Inputs!$B$56,Inputs!$B$55*(1+Inputs!$B$47),0)+IF(14>=Inputs!$B$58,Inputs!$B$57*(1+Inputs!$B$47),0) -> 0 | P48: =IF(15>=Inputs!$B$56,Inputs!$B$55*(1+Inputs!$B$47),0)+IF(15>=Inputs!$B$58,Inputs!$B$57*(1+Inputs!$B$47),0) -> 0 | Q48: =IF(16>=Inputs!$B$56,Inputs!$B$55*(1+Inputs!$B$47),0)+IF(16>=Inputs!$B$58,Inputs!$B$57*(1+Inputs!$B$47),0) -> 0 | R48: =IF(17>=Inputs!$B$56,Inputs!$B$55*(1+Inputs!$B$47),0)+IF(17>=Inputs!$B$58,Inputs!$B$57*(1+Inputs!$B$47),0) -> 0 | S48: =IF(18>=Inputs!$B$56,Inputs!$B$55*(1+Inputs!$B$47),0)+IF(18>=Inputs!$B$58,Inputs!$B$57*(1+Inputs!$B$47),0) -> 0 | T48: =IF(19>=Inputs!$B$56,Inputs!$B$55*(1+Inputs!$B$47),0)+IF(19>=Inputs!$B$58,Inputs!$B$57*(1+Inputs!$B$47),0) -> 7265.4 | U48: =IF(20>=Inputs!$B$56,Inputs!$B$55*(1+Inputs!$B$47),0)+IF(20>=Inputs!$B$58,Inputs!$B$57*(1+Inputs!$B$47),0) -> 7265.4 | V48: =IF(21>=Inputs!$B$56,Inputs!$B$55*(1+Inputs!$B$47),0)+IF(21>=Inputs!$B$58,Inputs!$B$57*(1+Inputs!$B$47),0) -> 7265.4 | W48: =IF(22>=Inputs!$B$56,Inputs!$B$55*(1+Inputs!$B$47),0)+IF(22>=Inputs!$B$58,Inputs!$B$57*(1+Inputs!$B$47),0) -> 7265.4 | X48: =IF(23>=Inputs!$B$56,Inputs!$B$55*(1+Inputs!$B$47),0)+IF(23>=Inputs!$B$58,Inputs!$B$57*(1+Inputs!$B$47),0) -> 7265.4 | Y48: =IF(24>=Inputs!$B$56,Inputs!$B$55*(1+Inputs!$B$47),0)+IF(24>=Inputs!$B$58,Inputs!$B$57*(1+Inputs!$B$47),0) -> 7265.4
A49: Office | B49: =IF(1>=Inputs!$B$60,Inputs!$B$59,0) -> 0 | C49: =IF(2>=Inputs!$B$60,Inputs!$B$59,0) -> 0 | D49: =IF(3>=Inputs!$B$60,Inputs!$B$59,0) -> 0 | E49: =IF(4>=Inputs!$B$60,Inputs!$B$59,0) -> 0 | F49: =IF(5>=Inputs!$B$60,Inputs!$B$59,0) -> 0 | G49: =IF(6>=Inputs!$B$60,Inputs!$B$59,0) -> 0 | H49: =IF(7>=Inputs!$B$60,Inputs!$B$59,0) -> 0 | I49: =IF(8>=Inputs!$B$60,Inputs!$B$59,0) -> 0 | J49: =IF(9>=Inputs!$B$60,Inputs!$B$59,0) -> 0 | K49: =IF(10>=Inputs!$B$60,Inputs!$B$59,0) -> 0 | L49: =IF(11>=Inputs!$B$60,Inputs!$B$59,0) -> 0 | M49: =IF(12>=Inputs!$B$60,Inputs!$B$59,0) -> 0 | N49: =IF(13>=Inputs!$B$60,Inputs!$B$59,0) -> 0 | O49: =IF(14>=Inputs!$B$60,Inputs!$B$59,0) -> 0 | P49: =IF(15>=Inputs!$B$60,Inputs!$B$59,0) -> 0 | Q49: =IF(16>=Inputs!$B$60,Inputs!$B$59,0) -> 0 | R49: =IF(17>=Inputs!$B$60,Inputs!$B$59,0) -> 0 | S49: =IF(18>=Inputs!$B$60,Inputs!$B$59,0) -> 0 | T49: =IF(19>=Inputs!$B$60,Inputs!$B$59,0) -> 0 | U49: =IF(20>=Inputs!$B$60,Inputs!$B$59,0) -> 0 | V49: =IF(21>=Inputs!$B$60,Inputs!$B$59,0) -> 0 | W49: =IF(22>=Inputs!$B$60,Inputs!$B$59,0) -> 0 | X49: =IF(23>=Inputs!$B$60,Inputs!$B$59,0) -> 0 | Y49: =IF(24>=Inputs!$B$60,Inputs!$B$59,0) -> 0
A50: Result before tax (MAD) | B50: =B44-B45-B46-B47-B48-B49 -> -2806.4033 | C50: =C44-C45-C46-C47-C48-C49 -> -1847.4106 | D50: =D44-D45-D46-D47-D48-D49 -> -902.80279 | E50: =E44-E45-E46-E47-E48-E49 -> 1001.2326 | F50: =F44-F45-F46-F47-F48-F49 -> 2876.7074 | G50: =G44-G45-G46-G47-G48-G49 -> 4724.0502 | H50: =H44-H45-H46-H47-H48-H49 -> 6543.6827 | I50: =I44-I45-I46-I47-I48-I49 -> 8336.0208 | ... Y50: =Y44-Y45-Y46-Y47-Y48-Y49 -> 4555.8364
A51: IS + cotisation minimale | B51: =MAX(B50*Inputs!$B$48,MAX(B44*Inputs!$B$49,250)) -> 250 | C51: =MAX(C50*Inputs!$B$48,MAX(C44*Inputs!$B$49,250)) -> 250 | D51: =MAX(D50*Inputs!$B$48,MAX(D44*Inputs!$B$49,250)) -> 250 | E51: =MAX(E50*Inputs!$B$48,MAX(E44*Inputs!$B$49,250)) -> 250 | F51: =MAX(F50*Inputs!$B$48,MAX(F44*Inputs!$B$49,250)) -> 575.34149 | G51: =MAX(G50*Inputs!$B$48,MAX(G44*Inputs!$B$49,250)) -> 944.81003 | H51: =MAX(H50*Inputs!$B$48,MAX(H44*Inputs!$B$49,250)) -> 1308.7365 | I51: =MAX(I50*Inputs!$B$48,MAX(I44*Inputs!$B$49,250)) -> 1667.2042 | ... Y51: =MAX(Y50*Inputs!$B$48,MAX(Y44*Inputs!$B$49,250)) -> 911.16728
A52: Net result after tax | B52: =B50-B51 -> -3056.4033 | C52: =C50-C51 -> -2097.4106 | D52: =D50-D51 -> -1152.8028 | E52: =E50-E51 -> 751.23258 | F52: =F50-F51 -> 2301.3659 | G52: =G50-G51 -> 3779.2401 | H52: =H50-H51 -> 5234.9462 | I52: =I50-I51 -> 6668.8167 | ... Y52: =Y50-Y51 -> 3644.6691
A53: Cumulative net after tax | B53: =B52 -> -3056.4033 | C53: =B53+C52 -> -5153.8139 | D53: =C53+D52 -> -6306.6167 | E53: =D53+E52 -> -5555.3842 | F53: =E53+F52 -> -3254.0182 | G53: =F53+G52 -> 525.22191 | H53: =G53+H52 -> 5760.1681 | I53: =H53+I52 -> 12428.985 | J53: =I53+J52 -> 20510.164 | ... Y53: =X53+Y52 -> 48968.695
A56: Cabinet-led (recommended focus)
A57: New accounts / month — Petit | B57: 1
A58: New accounts / month — Moyen | B58: 2
A59: New accounts / month — Grand | B59: 0.5
A60: New cabinets / month | B60: 0.6
A61: Monthly churn (accounts) | B61: 0.01
A62: Ramp: months 1–3 at 50% of the rate above
A63: Month | B63: 1 | C63: 2 | D63: 3 | E63: 4 | F63: 5 | G63: 6 | H63: 7 | I63: 8 | J63: 9 | K63: 10 | L63: 11 | M63: 12 | N63: 13 | O63: 14 | P63: 15 | Q63: 16 | R63: 17 | S63: 18 | T63: 19 | U63: 20 | V63: 21 | W63: 22 | X63: 23 | Y63: 24
A64: Active Petit accounts | B64: =$B$57*IF(1<=3,0.5,1) -> 0.5 | C64: =B64*(1-$B$61)+$B$57*IF(2<=3,0.5,1) -> 0.995 | D64: =C64*(1-$B$61)+$B$57*IF(3<=3,0.5,1) -> 1.48505 | E64: =D64*(1-$B$61)+$B$57*IF(4<=3,0.5,1) -> 2.4701995 | F64: =E64*(1-$B$61)+$B$57*IF(5<=3,0.5,1) -> 3.4454975 | G64: =F64*(1-$B$61)+$B$57*IF(6<=3,0.5,1) -> 4.4110425 | H64: =G64*(1-$B$61)+$B$57*IF(7<=3,0.5,1) -> 5.3669321 | I64: =H64*(1-$B$61)+$B$57*IF(8<=3,0.5,1) -> 6.3132628 | J64: =I64*(1-$B$61)+$B$57*IF(9<=3,0.5,1) -> 7.2501302 | K64: =J64*(1-$B$61)+$B$57*IF(10<=3,0.5,1) -> 8.1776289 | L64: =K64*(1-$B$61)+$B$57*IF(11<=3,0.5,1) -> 9.0958526 | M64: =L64*(1-$B$61)+$B$57*IF(12<=3,0.5,1) -> 10.004894 | N64: =M64*(1-$B$61)+$B$57*IF(13<=3,0.5,1) -> 10.904845 | O64: =N64*(1-$B$61)+$B$57*IF(14<=3,0.5,1) -> 11.795797 | P64: =O64*(1-$B$61)+$B$57*IF(15<=3,0.5,1) -> 12.677839 | Q64: =P64*(1-$B$61)+$B$57*IF(16<=3,0.5,1) -> 13.55106 | R64: =Q64*(1-$B$61)+$B$57*IF(17<=3,0.5,1) -> 14.41555 | S64: =R64*(1-$B$61)+$B$57*IF(18<=3,0.5,1) -> 15.271394 | T64: =S64*(1-$B$61)+$B$57*IF(19<=3,0.5,1) -> 16.11868 | U64: =T64*(1-$B$61)+$B$57*IF(20<=3,0.5,1) -> 16.957493 | V64: =U64*(1-$B$61)+$B$57*IF(21<=3,0.5,1) -> 17.787919 | W64: =V64*(1-$B$61)+$B$57*IF(22<=3,0.5,1) -> 18.610039 | X64: =W64*(1-$B$61)+$B$57*IF(23<=3,0.5,1) -> 19.423939 | Y64: =X64*(1-$B$61)+$B$57*IF(24<=3,0.5,1) -> 20.2297
A65: Active Moyen accounts | B65: =$B$58*IF(1<=3,0.5,1) -> 1 | C65: =B65*(1-$B$61)+$B$58*IF(2<=3,0.5,1) -> 1.99 | D65: =C65*(1-$B$61)+$B$58*IF(3<=3,0.5,1) -> 2.9701 | E65: =D65*(1-$B$61)+$B$58*IF(4<=3,0.5,1) -> 4.940399 | F65: =E65*(1-$B$61)+$B$58*IF(5<=3,0.5,1) -> 6.890995 | G65: =F65*(1-$B$61)+$B$58*IF(6<=3,0.5,1) -> 8.8220851 | H65: =G65*(1-$B$61)+$B$58*IF(7<=3,0.5,1) -> 10.733864 | I65: =H65*(1-$B$61)+$B$58*IF(8<=3,0.5,1) -> 12.626526 | J65: =I65*(1-$B$61)+$B$58*IF(9<=3,0.5,1) -> 14.50026 | K65: =J65*(1-$B$61)+$B$58*IF(10<=3,0.5,1) -> 16.355258 | L65: =K65*(1-$B$61)+$B$58*IF(11<=3,0.5,1) -> 18.191705 | M65: =L65*(1-$B$61)+$B$58*IF(12<=3,0.5,1) -> 20.009788 | N65: =M65*(1-$B$61)+$B$58*IF(13<=3,0.5,1) -> 21.80969 | O65: =N65*(1-$B$61)+$B$58*IF(14<=3,0.5,1) -> 23.591593 | P65: =O65*(1-$B$61)+$B$58*IF(15<=3,0.5,1) -> 25.355677 | Q65: =P65*(1-$B$61)+$B$58*IF(16<=3,0.5,1) -> 27.102121 | R65: =Q65*(1-$B$61)+$B$58*IF(17<=3,0.5,1) -> 28.831099 | S65: =R65*(1-$B$61)+$B$58*IF(18<=3,0.5,1) -> 30.542788 | T65: =S65*(1-$B$61)+$B$58*IF(19<=3,0.5,1) -> 32.237361 | U65: =T65*(1-$B$61)+$B$58*IF(20<=3,0.5,1) -> 33.914987 | V65: =U65*(1-$B$61)+$B$58*IF(21<=3,0.5,1) -> 35.575837 | W65: =V65*(1-$B$61)+$B$58*IF(22<=3,0.5,1) -> 37.220079 | X65: =W65*(1-$B$61)+$B$58*IF(23<=3,0.5,1) -> 38.847878 | Y65: =X65*(1-$B$61)+$B$58*IF(24<=3,0.5,1) -> 40.459399
A66: Active Grand accounts | B66: =$B$59*IF(1<=3,0.5,1) -> 0.25 | C66: =B66*(1-$B$61)+$B$59*IF(2<=3,0.5,1) -> 0.4975 | D66: =C66*(1-$B$61)+$B$59*IF(3<=3,0.5,1) -> 0.742525 | E66: =D66*(1-$B$61)+$B$59*IF(4<=3,0.5,1) -> 1.2350998 | F66: =E66*(1-$B$61)+$B$59*IF(5<=3,0.5,1) -> 1.7227488 | G66: =F66*(1-$B$61)+$B$59*IF(6<=3,0.5,1) -> 2.2055213 | H66: =G66*(1-$B$61)+$B$59*IF(7<=3,0.5,1) -> 2.6834661 | I66: =H66*(1-$B$61)+$B$59*IF(8<=3,0.5,1) -> 3.1566314 | J66: =I66*(1-$B$61)+$B$59*IF(9<=3,0.5,1) -> 3.6250651 | K66: =J66*(1-$B$61)+$B$59*IF(10<=3,0.5,1) -> 4.0888144 | L66: =K66*(1-$B$61)+$B$59*IF(11<=3,0.5,1) -> 4.5479263 | M66: =L66*(1-$B$61)+$B$59*IF(12<=3,0.5,1) -> 5.002447 | N66: =M66*(1-$B$61)+$B$59*IF(13<=3,0.5,1) -> 5.4524225 | O66: =N66*(1-$B$61)+$B$59*IF(14<=3,0.5,1) -> 5.8978983 | P66: =O66*(1-$B$61)+$B$59*IF(15<=3,0.5,1) -> 6.3389193 | Q66: =P66*(1-$B$61)+$B$59*IF(16<=3,0.5,1) -> 6.7755301 | R66: =Q66*(1-$B$61)+$B$59*IF(17<=3,0.5,1) -> 7.2077748 | S66: =R66*(1-$B$61)+$B$59*IF(18<=3,0.5,1) -> 7.6356971 | T66: =S66*(1-$B$61)+$B$59*IF(19<=3,0.5,1) -> 8.0593401 | U66: =T66*(1-$B$61)+$B$59*IF(20<=3,0.5,1) -> 8.4787467 | V66: =U66*(1-$B$61)+$B$59*IF(21<=3,0.5,1) -> 8.8939593 | W66: =V66*(1-$B$61)+$B$59*IF(22<=3,0.5,1) -> 9.3050197 | X66: =W66*(1-$B$61)+$B$59*IF(23<=3,0.5,1) -> 9.7119695 | Y66: =X66*(1-$B$61)+$B$59*IF(24<=3,0.5,1) -> 10.11485
A67: Active cabinets | B67: =$B$60*IF(1<=3,0.5,1) -> 0.3 | C67: =B67*(1-$B$61)+$B$60*IF(2<=3,0.5,1) -> 0.597 | D67: =C67*(1-$B$61)+$B$60*IF(3<=3,0.5,1) -> 0.89103 | E67: =D67*(1-$B$61)+$B$60*IF(4<=3,0.5,1) -> 1.4821197 | F67: =E67*(1-$B$61)+$B$60*IF(5<=3,0.5,1) -> 2.0672985 | G67: =F67*(1-$B$61)+$B$60*IF(6<=3,0.5,1) -> 2.6466255 | H67: =G67*(1-$B$61)+$B$60*IF(7<=3,0.5,1) -> 3.2201593 | I67: =H67*(1-$B$61)+$B$60*IF(8<=3,0.5,1) -> 3.7879577 | J67: =I67*(1-$B$61)+$B$60*IF(9<=3,0.5,1) -> 4.3500781 | K67: =J67*(1-$B$61)+$B$60*IF(10<=3,0.5,1) -> 4.9065773 | L67: =K67*(1-$B$61)+$B$60*IF(11<=3,0.5,1) -> 5.4575115 | M67: =L67*(1-$B$61)+$B$60*IF(12<=3,0.5,1) -> 6.0029364 | N67: =M67*(1-$B$61)+$B$60*IF(13<=3,0.5,1) -> 6.5429071 | O67: =N67*(1-$B$61)+$B$60*IF(14<=3,0.5,1) -> 7.077478 | P67: =O67*(1-$B$61)+$B$60*IF(15<=3,0.5,1) -> 7.6067032 | Q67: =P67*(1-$B$61)+$B$60*IF(16<=3,0.5,1) -> 8.1306362 | R67: =Q67*(1-$B$61)+$B$60*IF(17<=3,0.5,1) -> 8.6493298 | S67: =R67*(1-$B$61)+$B$60*IF(18<=3,0.5,1) -> 9.1628365 | T67: =S67*(1-$B$61)+$B$60*IF(19<=3,0.5,1) -> 9.6712082 | U67: =T67*(1-$B$61)+$B$60*IF(20<=3,0.5,1) -> 10.174496 | V67: =U67*(1-$B$61)+$B$60*IF(21<=3,0.5,1) -> 10.672751 | W67: =V67*(1-$B$61)+$B$60*IF(22<=3,0.5,1) -> 11.166024 | X67: =W67*(1-$B$61)+$B$60*IF(23<=3,0.5,1) -> 11.654363 | Y67: =X67*(1-$B$61)+$B$60*IF(24<=3,0.5,1) -> 12.13782
A68: Total paid lots | B68: =B64*Inputs!$B$35+B65*Inputs!$B$36+B66*Inputs!$B$37+B67*Inputs!$B$38 -> 322.5 | C68: =C64*Inputs!$B$35+C65*Inputs!$B$36+C66*Inputs!$B$37+C67*Inputs!$B$38 -> 641.775 | D68: =D64*Inputs!$B$35+D65*Inputs!$B$36+D66*Inputs!$B$37+D67*Inputs!$B$38 -> 957.85725 | E68: =E64*Inputs!$B$35+E65*Inputs!$B$36+E66*Inputs!$B$37+E67*Inputs!$B$38 -> 1593.2787 | F68: =F64*Inputs!$B$35+F65*Inputs!$B$36+F66*Inputs!$B$37+F67*Inputs!$B$38 -> 2222.3459 | G68: =G64*Inputs!$B$35+G65*Inputs!$B$36+G66*Inputs!$B$37+G67*Inputs!$B$38 -> 2845.1224 | H68: =H64*Inputs!$B$35+H65*Inputs!$B$36+H66*Inputs!$B$37+H67*Inputs!$B$38 -> 3461.6712 | I68: =I64*Inputs!$B$35+I65*Inputs!$B$36+I66*Inputs!$B$37+I67*Inputs!$B$38 -> 4072.0545 | ... Y68: =Y64*Inputs!$B$35+Y65*Inputs!$B$36+Y66*Inputs!$B$37+Y67*Inputs!$B$38 -> 13048.156
A69: Revenue TTC (MAD) | B69: =B64*'Unit economics'!$E$2+B65*'Unit economics'!$E$3+B66*'Unit economics'!$E$4+B67*'Unit economics'!$E$5 -> 1674.5 | C69: =C64*'Unit economics'!$E$2+C65*'Unit economics'!$E$3+C66*'Unit economics'!$E$4+C67*'Unit economics'!$E$5 -> 3332.255 | D69: =D64*'Unit economics'!$E$2+D65*'Unit economics'!$E$3+D66*'Unit economics'!$E$4+D67*'Unit economics'!$E$5 -> 4973.4325 | E69: =E64*'Unit economics'!$E$2+E65*'Unit economics'!$E$3+E66*'Unit economics'!$E$4+E67*'Unit economics'!$E$5 -> 8272.6981 | F69: =F64*'Unit economics'!$E$2+F65*'Unit economics'!$E$3+F66*'Unit economics'!$E$4+F67*'Unit economics'!$E$5 -> 11538.971 | G69: =G64*'Unit economics'!$E$2+G65*'Unit economics'!$E$3+G66*'Unit economics'!$E$4+G67*'Unit economics'!$E$5 -> 14772.581 | H69: =H64*'Unit economics'!$E$2+H65*'Unit economics'!$E$3+H66*'Unit economics'!$E$4+H67*'Unit economics'!$E$5 -> 17973.856 | I69: =I64*'Unit economics'!$E$2+I65*'Unit economics'!$E$3+I66*'Unit economics'!$E$4+I67*'Unit economics'!$E$5 -> 21143.117 | ... Y69: =Y64*'Unit economics'!$E$2+Y65*'Unit economics'!$E$3+Y66*'Unit economics'!$E$4+Y67*'Unit economics'!$E$5 -> 67749.264
A70: Revenue net of VAT | B70: =B69/(1+Inputs!$B$20) -> 1395.4167 | C70: =C69/(1+Inputs!$B$20) -> 2776.8792 | D70: =D69/(1+Inputs!$B$20) -> 4144.527 | E70: =E69/(1+Inputs!$B$20) -> 6893.9151 | F70: =F69/(1+Inputs!$B$20) -> 9615.8093 | G70: =G69/(1+Inputs!$B$20) -> 12310.485 | H70: =H69/(1+Inputs!$B$20) -> 14978.213 | I70: =I69/(1+Inputs!$B$20) -> 17619.264 | ... Y70: =Y69/(1+Inputs!$B$20) -> 56457.72
A71: Variable costs (SMS + support) | B71: =B64*('Unit economics'!$H$2+'Unit economics'!$I$2)+B65*('Unit economics'!$H$3+'Unit economics'!$I$3)+B66*('Unit economics'!$H$4+'Unit economics'!$I$4)+B67*('Unit economics'!$H$5+'Unit economics'!$I$5) -> 277.95 | C71: =C64*('Unit economics'!$H$2+'Unit economics'!$I$2)+C65*('Unit economics'!$H$3+'Unit economics'!$I$3)+C66*('Unit economics'!$H$4+'Unit economics'!$I$4)+C67*('Unit economics'!$H$5+'Unit economics'!$I$5) -> 553.1205 | D71: =D64*('Unit economics'!$H$2+'Unit economics'!$I$2)+D65*('Unit economics'!$H$3+'Unit economics'!$I$3)+D66*('Unit economics'!$H$4+'Unit economics'!$I$4)+D67*('Unit economics'!$H$5+'Unit economics'!$I$5) -> 825.5393 | E71: =E64*('Unit economics'!$H$2+'Unit economics'!$I$2)+E65*('Unit economics'!$H$3+'Unit economics'!$I$3)+E66*('Unit economics'!$H$4+'Unit economics'!$I$4)+E67*('Unit economics'!$H$5+'Unit economics'!$I$5) -> 1373.1839 | F71: =F64*('Unit economics'!$H$2+'Unit economics'!$I$2)+F65*('Unit economics'!$H$3+'Unit economics'!$I$3)+F66*('Unit economics'!$H$4+'Unit economics'!$I$4)+F67*('Unit economics'!$H$5+'Unit economics'!$I$5) -> 1915.3521 | G71: =G64*('Unit economics'!$H$2+'Unit economics'!$I$2)+G65*('Unit economics'!$H$3+'Unit economics'!$I$3)+G66*('Unit economics'!$H$4+'Unit economics'!$I$4)+G67*('Unit economics'!$H$5+'Unit economics'!$I$5) -> 2452.0985 | H71: =H64*('Unit economics'!$H$2+'Unit economics'!$I$2)+H65*('Unit economics'!$H$3+'Unit economics'!$I$3)+H66*('Unit economics'!$H$4+'Unit economics'!$I$4)+H67*('Unit economics'!$H$5+'Unit economics'!$I$5) -> 2983.4776 | I71: =I64*('Unit economics'!$H$2+'Unit economics'!$I$2)+I65*('Unit economics'!$H$3+'Unit economics'!$I$3)+I66*('Unit economics'!$H$4+'Unit economics'!$I$4)+I67*('Unit economics'!$H$5+'Unit economics'!$I$5) -> 3509.5428 | ... Y71: =Y64*('Unit economics'!$H$2+'Unit economics'!$I$2)+Y65*('Unit economics'!$H$3+'Unit economics'!$I$3)+Y66*('Unit economics'!$H$4+'Unit economics'!$I$4)+Y67*('Unit economics'!$H$5+'Unit economics'!$I$5) -> 11245.69
A72: Infra fixed costs + accountant | B72: =Inputs!$B$10+Inputs!$B$46 -> 3780 | C72: =Inputs!$B$10+Inputs!$B$46 -> 3780 | D72: =Inputs!$B$10+Inputs!$B$46 -> 3780 | E72: =Inputs!$B$10+Inputs!$B$46 -> 3780 | F72: =Inputs!$B$10+Inputs!$B$46 -> 3780 | G72: =Inputs!$B$10+Inputs!$B$46 -> 3780 | H72: =Inputs!$B$10+Inputs!$B$46 -> 3780 | I72: =Inputs!$B$10+Inputs!$B$46 -> 3780 | ... Y72: =Inputs!$B$10+Inputs!$B$46 -> 3780
A73: Founder salaries (incl. CNSS) | B73: =IF(1>=Inputs!$B$54,Inputs!$B$52*Inputs!$B$53*(1+Inputs!$B$47),0) -> 0 | C73: =IF(2>=Inputs!$B$54,Inputs!$B$52*Inputs!$B$53*(1+Inputs!$B$47),0) -> 0 | D73: =IF(3>=Inputs!$B$54,Inputs!$B$52*Inputs!$B$53*(1+Inputs!$B$47),0) -> 0 | E73: =IF(4>=Inputs!$B$54,Inputs!$B$52*Inputs!$B$53*(1+Inputs!$B$47),0) -> 0 | F73: =IF(5>=Inputs!$B$54,Inputs!$B$52*Inputs!$B$53*(1+Inputs!$B$47),0) -> 0 | G73: =IF(6>=Inputs!$B$54,Inputs!$B$52*Inputs!$B$53*(1+Inputs!$B$47),0) -> 0 | H73: =IF(7>=Inputs!$B$54,Inputs!$B$52*Inputs!$B$53*(1+Inputs!$B$47),0) -> 0 | I73: =IF(8>=Inputs!$B$54,Inputs!$B$52*Inputs!$B$53*(1+Inputs!$B$47),0) -> 0 | J73: =IF(9>=Inputs!$B$54,Inputs!$B$52*Inputs!$B$53*(1+Inputs!$B$47),0) -> 0 | K73: =IF(10>=Inputs!$B$54,Inputs!$B$52*Inputs!$B$53*(1+Inputs!$B$47),0) -> 0 | L73: =IF(11>=Inputs!$B$54,Inputs!$B$52*Inputs!$B$53*(1+Inputs!$B$47),0) -> 0 | M73: =IF(12>=Inputs!$B$54,Inputs!$B$52*Inputs!$B$53*(1+Inputs!$B$47),0) -> 0 | N73: =IF(13>=Inputs!$B$54,Inputs!$B$52*Inputs!$B$53*(1+Inputs!$B$47),0) -> 21796.2 | O73: =IF(14>=Inputs!$B$54,Inputs!$B$52*Inputs!$B$53*(1+Inputs!$B$47),0) -> 21796.2 | P73: =IF(15>=Inputs!$B$54,Inputs!$B$52*Inputs!$B$53*(1+Inputs!$B$47),0) -> 21796.2 | Q73: =IF(16>=Inputs!$B$54,Inputs!$B$52*Inputs!$B$53*(1+Inputs!$B$47),0) -> 21796.2 | R73: =IF(17>=Inputs!$B$54,Inputs!$B$52*Inputs!$B$53*(1+Inputs!$B$47),0) -> 21796.2 | S73: =IF(18>=Inputs!$B$54,Inputs!$B$52*Inputs!$B$53*(1+Inputs!$B$47),0) -> 21796.2 | T73: =IF(19>=Inputs!$B$54,Inputs!$B$52*Inputs!$B$53*(1+Inputs!$B$47),0) -> 21796.2 | U73: =IF(20>=Inputs!$B$54,Inputs!$B$52*Inputs!$B$53*(1+Inputs!$B$47),0) -> 21796.2 | V73: =IF(21>=Inputs!$B$54,Inputs!$B$52*Inputs!$B$53*(1+Inputs!$B$47),0) -> 21796.2 | W73: =IF(22>=Inputs!$B$54,Inputs!$B$52*Inputs!$B$53*(1+Inputs!$B$47),0) -> 21796.2 | X73: =IF(23>=Inputs!$B$54,Inputs!$B$52*Inputs!$B$53*(1+Inputs!$B$47),0) -> 21796.2 | Y73: =IF(24>=Inputs!$B$54,Inputs!$B$52*Inputs!$B$53*(1+Inputs!$B$47),0) -> 21796.2
A74: Hires (incl. CNSS) | B74: =IF(1>=Inputs!$B$56,Inputs!$B$55*(1+Inputs!$B$47),0)+IF(1>=Inputs!$B$58,Inputs!$B$57*(1+Inputs!$B$47),0) -> 0 | C74: =IF(2>=Inputs!$B$56,Inputs!$B$55*(1+Inputs!$B$47),0)+IF(2>=Inputs!$B$58,Inputs!$B$57*(1+Inputs!$B$47),0) -> 0 | D74: =IF(3>=Inputs!$B$56,Inputs!$B$55*(1+Inputs!$B$47),0)+IF(3>=Inputs!$B$58,Inputs!$B$57*(1+Inputs!$B$47),0) -> 0 | E74: =IF(4>=Inputs!$B$56,Inputs!$B$55*(1+Inputs!$B$47),0)+IF(4>=Inputs!$B$58,Inputs!$B$57*(1+Inputs!$B$47),0) -> 0 | F74: =IF(5>=Inputs!$B$56,Inputs!$B$55*(1+Inputs!$B$47),0)+IF(5>=Inputs!$B$58,Inputs!$B$57*(1+Inputs!$B$47),0) -> 0 | G74: =IF(6>=Inputs!$B$56,Inputs!$B$55*(1+Inputs!$B$47),0)+IF(6>=Inputs!$B$58,Inputs!$B$57*(1+Inputs!$B$47),0) -> 0 | H74: =IF(7>=Inputs!$B$56,Inputs!$B$55*(1+Inputs!$B$47),0)+IF(7>=Inputs!$B$58,Inputs!$B$57*(1+Inputs!$B$47),0) -> 0 | I74: =IF(8>=Inputs!$B$56,Inputs!$B$55*(1+Inputs!$B$47),0)+IF(8>=Inputs!$B$58,Inputs!$B$57*(1+Inputs!$B$47),0) -> 0 | J74: =IF(9>=Inputs!$B$56,Inputs!$B$55*(1+Inputs!$B$47),0)+IF(9>=Inputs!$B$58,Inputs!$B$57*(1+Inputs!$B$47),0) -> 0 | K74: =IF(10>=Inputs!$B$56,Inputs!$B$55*(1+Inputs!$B$47),0)+IF(10>=Inputs!$B$58,Inputs!$B$57*(1+Inputs!$B$47),0) -> 0 | L74: =IF(11>=Inputs!$B$56,Inputs!$B$55*(1+Inputs!$B$47),0)+IF(11>=Inputs!$B$58,Inputs!$B$57*(1+Inputs!$B$47),0) -> 0 | M74: =IF(12>=Inputs!$B$56,Inputs!$B$55*(1+Inputs!$B$47),0)+IF(12>=Inputs!$B$58,Inputs!$B$57*(1+Inputs!$B$47),0) -> 0 | N74: =IF(13>=Inputs!$B$56,Inputs!$B$55*(1+Inputs!$B$47),0)+IF(13>=Inputs!$B$58,Inputs!$B$57*(1+Inputs!$B$47),0) -> 0 | O74: =IF(14>=Inputs!$B$56,Inputs!$B$55*(1+Inputs!$B$47),0)+IF(14>=Inputs!$B$58,Inputs!$B$57*(1+Inputs!$B$47),0) -> 0 | P74: =IF(15>=Inputs!$B$56,Inputs!$B$55*(1+Inputs!$B$47),0)+IF(15>=Inputs!$B$58,Inputs!$B$57*(1+Inputs!$B$47),0) -> 0 | Q74: =IF(16>=Inputs!$B$56,Inputs!$B$55*(1+Inputs!$B$47),0)+IF(16>=Inputs!$B$58,Inputs!$B$57*(1+Inputs!$B$47),0) -> 0 | R74: =IF(17>=Inputs!$B$56,Inputs!$B$55*(1+Inputs!$B$47),0)+IF(17>=Inputs!$B$58,Inputs!$B$57*(1+Inputs!$B$47),0) -> 0 | S74: =IF(18>=Inputs!$B$56,Inputs!$B$55*(1+Inputs!$B$47),0)+IF(18>=Inputs!$B$58,Inputs!$B$57*(1+Inputs!$B$47),0) -> 0 | T74: =IF(19>=Inputs!$B$56,Inputs!$B$55*(1+Inputs!$B$47),0)+IF(19>=Inputs!$B$58,Inputs!$B$57*(1+Inputs!$B$47),0) -> 7265.4 | U74: =IF(20>=Inputs!$B$56,Inputs!$B$55*(1+Inputs!$B$47),0)+IF(20>=Inputs!$B$58,Inputs!$B$57*(1+Inputs!$B$47),0) -> 7265.4 | V74: =IF(21>=Inputs!$B$56,Inputs!$B$55*(1+Inputs!$B$47),0)+IF(21>=Inputs!$B$58,Inputs!$B$57*(1+Inputs!$B$47),0) -> 7265.4 | W74: =IF(22>=Inputs!$B$56,Inputs!$B$55*(1+Inputs!$B$47),0)+IF(22>=Inputs!$B$58,Inputs!$B$57*(1+Inputs!$B$47),0) -> 7265.4 | X74: =IF(23>=Inputs!$B$56,Inputs!$B$55*(1+Inputs!$B$47),0)+IF(23>=Inputs!$B$58,Inputs!$B$57*(1+Inputs!$B$47),0) -> 7265.4 | Y74: =IF(24>=Inputs!$B$56,Inputs!$B$55*(1+Inputs!$B$47),0)+IF(24>=Inputs!$B$58,Inputs!$B$57*(1+Inputs!$B$47),0) -> 7265.4
A75: Office | B75: =IF(1>=Inputs!$B$60,Inputs!$B$59,0) -> 0 | C75: =IF(2>=Inputs!$B$60,Inputs!$B$59,0) -> 0 | D75: =IF(3>=Inputs!$B$60,Inputs!$B$59,0) -> 0 | E75: =IF(4>=Inputs!$B$60,Inputs!$B$59,0) -> 0 | F75: =IF(5>=Inputs!$B$60,Inputs!$B$59,0) -> 0 | G75: =IF(6>=Inputs!$B$60,Inputs!$B$59,0) -> 0 | H75: =IF(7>=Inputs!$B$60,Inputs!$B$59,0) -> 0 | I75: =IF(8>=Inputs!$B$60,Inputs!$B$59,0) -> 0 | J75: =IF(9>=Inputs!$B$60,Inputs!$B$59,0) -> 0 | K75: =IF(10>=Inputs!$B$60,Inputs!$B$59,0) -> 0 | L75: =IF(11>=Inputs!$B$60,Inputs!$B$59,0) -> 0 | M75: =IF(12>=Inputs!$B$60,Inputs!$B$59,0) -> 0 | N75: =IF(13>=Inputs!$B$60,Inputs!$B$59,0) -> 0 | O75: =IF(14>=Inputs!$B$60,Inputs!$B$59,0) -> 0 | P75: =IF(15>=Inputs!$B$60,Inputs!$B$59,0) -> 0 | Q75: =IF(16>=Inputs!$B$60,Inputs!$B$59,0) -> 0 | R75: =IF(17>=Inputs!$B$60,Inputs!$B$59,0) -> 0 | S75: =IF(18>=Inputs!$B$60,Inputs!$B$59,0) -> 0 | T75: =IF(19>=Inputs!$B$60,Inputs!$B$59,0) -> 0 | U75: =IF(20>=Inputs!$B$60,Inputs!$B$59,0) -> 0 | V75: =IF(21>=Inputs!$B$60,Inputs!$B$59,0) -> 0 | W75: =IF(22>=Inputs!$B$60,Inputs!$B$59,0) -> 0 | X75: =IF(23>=Inputs!$B$60,Inputs!$B$59,0) -> 0 | Y75: =IF(24>=Inputs!$B$60,Inputs!$B$59,0) -> 0
A76: Result before tax (MAD) | B76: =B70-B71-B72-B73-B74-B75 -> -2662.5333 | C76: =C70-C71-C72-C73-C74-C75 -> -1556.2413 | D76: =D70-D71-D72-D73-D74-D75 -> -461.01225 | E76: =E70-E71-E72-E73-E74-E75 -> 1740.7312 | F76: =F70-F71-F72-F73-F74-F75 -> 3920.4572 | G76: =G70-G71-G72-G73-G74-G75 -> 6078.386 | H76: =H70-H71-H72-H73-H74-H75 -> 8214.7355 | I76: =I70-I71-I72-I73-I74-I75 -> 10329.721 | ... Y76: =Y70-Y71-Y72-Y73-Y74-Y75 -> 12370.43
A77: IS + cotisation minimale | B77: =MAX(B76*Inputs!$B$48,MAX(B70*Inputs!$B$49,250)) -> 250 | C77: =MAX(C76*Inputs!$B$48,MAX(C70*Inputs!$B$49,250)) -> 250 | D77: =MAX(D76*Inputs!$B$48,MAX(D70*Inputs!$B$49,250)) -> 250 | E77: =MAX(E76*Inputs!$B$48,MAX(E70*Inputs!$B$49,250)) -> 348.14624 | F77: =MAX(F76*Inputs!$B$48,MAX(F70*Inputs!$B$49,250)) -> 784.09144 | G77: =MAX(G76*Inputs!$B$48,MAX(G70*Inputs!$B$49,250)) -> 1215.6772 | H77: =MAX(H76*Inputs!$B$48,MAX(H70*Inputs!$B$49,250)) -> 1642.9471 | I77: =MAX(I76*Inputs!$B$48,MAX(I70*Inputs!$B$49,250)) -> 2065.9443 | ... Y77: =MAX(Y76*Inputs!$B$48,MAX(Y70*Inputs!$B$49,250)) -> 2474.086
A78: Net result after tax | B78: =B76-B77 -> -2912.5333 | C78: =C76-C77 -> -1806.2413 | D78: =D76-D77 -> -711.01225 | E78: =E76-E77 -> 1392.585 | F78: =F76-F77 -> 3136.3658 | G78: =G76-G77 -> 4862.7088 | H78: =H76-H77 -> 6571.7884 | I78: =I76-I77 -> 8263.7771 | ... Y78: =Y76-Y77 -> 9896.3439
A79: Cumulative net after tax | B79: =B78 -> -2912.5333 | C79: =B79+C78 -> -4718.7747 | D79: =C79+D78 -> -5429.7869 | E79: =D79+E78 -> -4037.202 | F79: =E79+F78 -> -900.83618 | G79: =F79+G78 -> 3961.8726 | H79: =G79+H78 -> 10533.661 | I79: =H79+I78 -> 18797.438 | J79: =I79+J78 -> 28736.284 | ... Y79: =X79+Y78 -> 123124.24
A82: Summary at month 12 and 24
A83: Scenario | B83: Lots M12 | C83: Net after tax M12 | D83: Lots M24 | E83: Net after tax M24 | F83: Cumulative M24 | G83: Months profitable (of 24) | H83: Deepest cumulative loss (cash needed)
A84: Slow (résistance wins) | B84: =M16 -> 1616.7567 | C84: =M26 -> 2581.8504 | D84: =Y16 -> 3093.2218 | E84: =Y26 -> -19685.023 | F84: =Y27 -> -233159.26 | G84: =COUNTIF(B26:Y26,">0") -> 5 | H84: =MIN(0,MIN(B27:Y27)) -> -233159.26
A85: Base (plan works) | B85: =M42 -> 4561.7377 | C85: =M52 -> 12192.42 | D85: =Y42 -> 8969.116 | E85: =Y52 -> 3644.6691 | F85: =Y53 -> 48968.695 | G85: =COUNTIF(B52:Y52,">0") -> 15 | H85: =MIN(0,MIN(B53:Y53)) -> -6306.6167
A86: Cabinet-led (recommended focus) | B86: =M68 -> 6453.1567 | C86: =M78 -> 14864.217 | D86: =Y68 -> 13048.156 | E86: =Y78 -> 9896.3439 | F86: =Y79 -> 123124.24 | G86: =COUNTIF(B78:Y78,">0") -> 20 | H86: =MIN(0,MIN(B79:Y79)) -> -5429.7869
A88: Capital note: 10 000 MAD share capital covers roughly three months of infrastructure. The 'deepest cumulative loss' column is the cash the founders must inject (or defer as unpaid salary) before the company self-funds.
